Workbook

Sheet Programa
A1: Nivel | B1: CURSO-Agenda | C1: NRC | D1: Semestre | E1: CodMaestroOferta | F1: Nombre Curso Oferta | G1: Nombre Curso | H1: CodMaestro | I1: NombreCursoOferta | J1: CodCursoOferta | K1: IdPlantilla | L1: IdSemestre | M1: IDCURSO | N1: URL
A2: =_xlfn.XLOOKUP(Tabla1[[#This Row],[CodMaestro]],UnidadesOrganizaciones!D:D,UnidadesOrganizaciones!L:L,"***") -> CVFA | B2: Gestión de tiempos, riesgos y costos A | C2: 63604 | D2: 202341 | E2: =_xlfn.TEXTBEFORE(H2,"MaestroP") -> #N/A | F2: =_xlfn.XLOOKUP(Tabla1[[#This Row],[CodMaestro]],UnidadesOrganizaciones!D:D,UnidadesOrganizaciones!C:C,"***") -> GESTIÓN DE TIEMPOS, RIESGOS Y COSTOS -MaestroC | G2: =LEFT(F2,FIND(" -",F2&" -")-1) -> GESTIÓN DE TIEMPOS, RIESGOS Y COSTOS | H2: CEOE-0320-MaestroC | I2: =Tabla1[[#This Row],[Nombre Curso]]&" - "&Tabla1[[#This Row],[Semestre]]&"-"&Tabla1[[#This Row],[NRC]] -> GESTIÓN DE TIEMPOS, RIESGOS Y COSTOS - 202341-63604 | J2: =E2&D2&"-"&C2 -> #N/A | K2: =_xlfn.XLOOKUP(Tabla1[[#This Row],[CodMaestro]],UnidadesOrganizaciones!D:D,UnidadesOrganizaciones!Q:Q,"***") -> 6691 | L2: =_xlfn.XLOOKUP(TEXT(Tabla1[[#This Row],[Semestre]],"######"),'CursosBS'!E:E,'CursosBS'!A:A,"***") -> 40978 | M2: =_xlfn.XLOOKUP(Tabla1[[#This Row],[CodCursoOferta]],'CursosBS'!E:E,'CursosBS'!A:A,"*NoExiste*") -> #N/A | N2: ="https://virtual.upb.edu.co/d2l/home/"&Tabla1[[#This Row],[IDCURSO]] -> #N/A
A3: =_xlfn.XLOOKUP(Tabla1[[#This Row],[CodMaestro]],UnidadesOrganizaciones!D:D,UnidadesOrganizaciones!L:L,"***") -> CVFC | B3: Emprendimiento Nivel Básico | C3: 51277 | D3: 202650 | E3: =_xlfn.TEXTBEFORE(H3,"MaestroP") -> ADEM-3173- | F3: =_xlfn.XLOOKUP(Tabla1[[#This Row],[CodMaestro]],UnidadesOrganizaciones!D:D,UnidadesOrganizaciones!C:C,"***") -> Emprendimiento Nivel Básico -QMMaestroP(R) | G3: =LEFT(F3,FIND(" -",F3&" -")-1) -> Emprendimiento Nivel Básico | H3: ADEM-3173-MaestroP | I3: =Tabla1[[#This Row],[Nombre Curso]]&" - "&Tabla1[[#This Row],[Semestre]]&"-"&Tabla1[[#This Row],[NRC]] -> Emprendimiento Nivel Básico - 202650-51277 | J3: =E3&D3&"-"&C3 -> ADEM-3173-202650-51277 | K3: =_xlfn.XLOOKUP(Tabla1[[#This Row],[CodMaestro]],UnidadesOrganizaciones!D:D,UnidadesOrganizaciones!Q:Q,"***") -> 38966 | L3: =_xlfn.XLOOKUP(TEXT(Tabla1[[#This Row],[Semestre]],"######"),'CursosBS'!E:E,'CursosBS'!A:A,"***") -> 77362 | M3: =_xlfn.XLOOKUP(Tabla1[[#This Row],[CodCursoOferta]],'CursosBS'!E:E,'CursosBS'!A:A,"*NoExiste*") -> *NoExiste* | N3: ="https://virtual.upb.edu.co/d2l/home/"&Tabla1[[#This Row],[IDCURSO]] -> https://virtual.upb.edu.co/d2l/home/*NoExiste*
A4: =_xlfn.XLOOKUP(Tabla1[[#This Row],[CodMaestro]],UnidadesOrganizaciones!D:D,UnidadesOrganizaciones!L:L,"***") -> CVFC | B4: Emprendimiento Nivel Básico | C4: 51278 | D4: 202650 | E4: =_xlfn.TEXTBEFORE(H4,"MaestroP") -> ADEM-3173- | F4: =_xlfn.XLOOKUP(Tabla1[[#This Row],[CodMaestro]],UnidadesOrganizaciones!D:D,UnidadesOrganizaciones!C:C,"***") -> Emprendimiento Nivel Básico -QMMaestroP(R) | G4: =LEFT(F4,FIND(" -",F4&" -")-1) -> Emprendimiento Nivel Básico | H4: ADEM-3173-MaestroP | I4: =Tabla1[[#This Row],[Nombre Curso]]&" - "&Tabla1[[#This Row],[Semestre]]&"-"&Tabla1[[#This Row],[NRC]] -> Emprendimiento Nivel Básico - 202650-51278 | J4: =E4&D4&"-"&C4 -> ADEM-3173-202650-51278 | K4: =_xlfn.XLOOKUP(Tabla1[[#This Row],[CodMaestro]],UnidadesOrganizaciones!D:D,UnidadesOrganizaciones!Q:Q,"***") -> 38966 | L4: =_xlfn.XLOOKUP(TEXT(Tabla1[[#This Row],[Semestre]],"######"),'CursosBS'!E:E,'CursosBS'!A:A,"***") -> 77362 | M4: =_xlfn.XLOOKUP(Tabla1[[#This Row],[CodCursoOferta]],'CursosBS'!E:E,'CursosBS'!A:A,"*NoExiste*") -> *NoExiste* | N4: ="https://virtual.upb.edu.co/d2l/home/"&Tabla1[[#This Row],[IDCURSO]] -> https://virtual.upb.edu.co/d2l/home/*NoExiste*
A5: =_xlfn.XLOOKUP(Tabla1[[#This Row],[CodMaestro]],UnidadesOrganizaciones!D:D,UnidadesOrganizaciones!L:L,"***") -> CVFC | B5: Emprendimiento Nivel Básico | C5: 51279 | D5: 202650 | E5: =_xlfn.TEXTBEFORE(H5,"MaestroP") -> ADEM-3173- | F5: =_xlfn.XLOOKUP(Tabla1[[#This Row],[CodMaestro]],UnidadesOrganizaciones!D:D,UnidadesOrganizaciones!C:C,"***") -> Emprendimiento Nivel Básico -QMMaestroP(R) | G5: =LEFT(F5,FIND(" -",F5&" -")-1) -> Emprendimiento Nivel Básico | H5: ADEM-3173-MaestroP | I5: =Tabla1[[#This Row],[Nombre Curso]]&" - "&Tabla1[[#This Row],[Semestre]]&"-"&Tabla1[[#This Row],[NRC]] -> Emprendimiento Nivel Básico - 202650-51279 | J5: =E5&D5&"-"&C5 -> ADEM-3173-202650-51279 | K5: =_xlfn.XLOOKUP(Tabla1[[#This Row],[CodMaestro]],UnidadesOrganizaciones!D:D,UnidadesOrganizaciones!Q:Q,"***") -> 38966 | L5: =_xlfn.XLOOKUP(TEXT(Tabla1[[#This Row],[Semestre]],"######"),'CursosBS'!E:E,'CursosBS'!A:A,"***") -> 77362 | M5: =_xlfn.XLOOKUP(Tabla1[[#This Row],[CodCursoOferta]],'CursosBS'!E:E,'CursosBS'!A:A,"*NoExiste*") -> *NoExiste* | N5: ="https://virtual.upb.edu.co/d2l/home/"&Tabla1[[#This Row],[IDCURSO]] -> https://virtual.upb.edu.co/d2l/home/*NoExiste*
A6: =_xlfn.XLOOKUP(Tabla1[[#This Row],[CodMaestro]],UnidadesOrganizaciones!D:D,UnidadesOrganizaciones!L:L,"***") -> CVFC | B6: Emprendimiento Nivel Básico | C6: 51280 | D6: 202650 | E6: =_xlfn.TEXTBEFORE(H6,"MaestroP") -> ADEM-3173- | F6: =_xlfn.XLOOKUP(Tabla1[[#This Row],[CodMaestro]],UnidadesOrganizaciones!D:D,UnidadesOrganizaciones!C:C,"***") -> Emprendimiento Nivel Básico -QMMaestroP(R) | G6: =LEFT(F6,FIND(" -",F6&" -")-1) -> Emprendimiento Nivel Básico | H6: ADEM-3173-MaestroP | I6: =Tabla1[[#This Row],[Nombre Curso]]&" - "&Tabla1[[#This Row],[Semestre]]&"-"&Tabla1[[#This Row],[NRC]] -> Emprendimiento Nivel Básico - 202650-51280 | J6: =E6&D6&"-"&C6 -> ADEM-3173-202650-51280 | K6: =_xlfn.XLOOKUP(Tabla1[[#This Row],[CodMaestro]],UnidadesOrganizaciones!D:D,UnidadesOrganizaciones!Q:Q,"***") -> 38966 | L6: =_xlfn.XLOOKUP(TEXT(Tabla1[[#This Row],[Semestre]],"######"),'CursosBS'!E:E,'CursosBS'!A:A,"***") -> 77362 | M6: =_xlfn.XLOOKUP(Tabla1[[#This Row],[CodCursoOferta]],'CursosBS'!E:E,'CursosBS'!A:A,"*NoExiste*") -> *NoExiste* | N6: ="https://virtual.upb.edu.co/d2l/home/"&Tabla1[[#This Row],[IDCURSO]] -> https://virtual.upb.edu.co/d2l/home/*NoExiste*
A7: =_xlfn.XLOOKUP(Tabla1[[#This Row],[CodMaestro]],UnidadesOrganizaciones!D:D,UnidadesOrganizaciones!L:L,"***") -> CVFC | B7: Emprendimiento Nivel Básico | C7: 51281 | D7: 202650 | E7: =_xlfn.TEXTBEFORE(H7,"MaestroP") -> ADEM-3173- | F7: =_xlfn.XLOOKUP(Tabla1[[#This Row],[CodMaestro]],UnidadesOrganizaciones!D:D,UnidadesOrganizaciones!C:C,"***") -> Emprendimiento Nivel Básico -QMMaestroP(R) | G7: =LEFT(F7,FIND(" -",F7&" -")-1) -> Emprendimiento Nivel Básico | H7: ADEM-3173-MaestroP | I7: =Tabla1[[#This Row],[Nombre Curso]]&" - "&Tabla1[[#This Row],[Semestre]]&"-"&Tabla1[[#This Row],[NRC]] -> Emprendimiento Nivel Básico - 202650-51281 | J7: =E7&D7&"-"&C7 -> ADEM-3173-202650-51281 | K7: =_xlfn.XLOOKUP(Tabla1[[#This Row],[CodMaestro]],UnidadesOrganizaciones!D:D,UnidadesOrganizaciones!Q:Q,"***") -> 38966 | L7: =_xlfn.XLOOKUP(TEXT(Tabla1[[#This Row],[Semestre]],"######"),'CursosBS'!E:E,'CursosBS'!A:A,"***") -> 77362 | M7: =_xlfn.XLOOKUP(Tabla1[[#This Row],[CodCursoOferta]],'CursosBS'!E:E,'CursosBS'!A:A,"*NoExiste*") -> *NoExiste* | N7: ="https://virtual.upb.edu.co/d2l/home/"&Tabla1[[#This Row],[IDCURSO]] -> https://virtual.upb.edu.co/d2l/home/*NoExiste*
A8: =_xlfn.XLOOKUP(Tabla1[[#This Row],[CodMaestro]],UnidadesOrganizaciones!D:D,UnidadesOrganizaciones!L:L,"***") -> CVFC | B8: Emprendimiento Nivel Básico | C8: 51282 | D8: 202650 | E8: =_xlfn.TEXTBEFORE(H8,"MaestroP") -> ADEM-3173- | F8: =_xlfn.XLOOKUP(Tabla1[[#This Row],[CodMaestro]],UnidadesOrganizaciones!D:D,UnidadesOrganizaciones!C:C,"***") -> Emprendimiento Nivel Básico -QMMaestroP(R) | G8: =LEFT(F8,FIND(" -",F8&" -")-1) -> Emprendimiento Nivel Básico | H8: ADEM-3173-MaestroP | I8: =Tabla1[[#This Row],[Nombre Curso]]&" - "&Tabla1[[#This Row],[Semestre]]&"-"&Tabla1[[#This Row],[NRC]] -> Emprendimiento Nivel Básico - 202650-51282 | J8: =E8&D8&"-"&C8 -> ADEM-3173-202650-51282 | K8: =_xlfn.XLOOKUP(Tabla1[[#This Row],[CodMaestro]],UnidadesOrganizaciones!D:D,UnidadesOrganizaciones!Q:Q,"***") -> 38966 | L8: =_xlfn.XLOOKUP(TEXT(Tabla1[[#This Row],[Semestre]],"######"),'CursosBS'!E:E,'CursosBS'!A:A,"***") -> 77362 | M8: =_xlfn.XLOOKUP(Tabla1[[#This Row],[CodCursoOferta]],'CursosBS'!E:E,'CursosBS'!A:A,"*NoExiste*") -> *NoExiste* | N8: ="https://virtual.upb.edu.co/d2l/home/"&Tabla1[[#This Row],[IDCURSO]] -> https://virtual.upb.edu.co/d2l/home/*NoExiste*
A9: =_xlfn.XLOOKUP(Tabla1[[#This Row],[CodMaestro]],UnidadesOrganizaciones!D:D,UnidadesOrganizaciones!L:L,"***") -> CVFC | B9: Emprendimiento Nivel Básico | C9: 51283 | D9: 202650 | E9: =_xlfn.TEXTBEFORE(H9,"MaestroP") -> ADEM-3173- | F9: =_xlfn.XLOOKUP(Tabla1[[#This Row],[CodMaestro]],UnidadesOrganizaciones!D:D,UnidadesOrganizaciones!C:C,"***") -> Emprendimiento Nivel Básico -QMMaestroP(R) | G9: =LEFT(F9,FIND(" -",F9&" -")-1) -> Emprendimiento Nivel Básico | H9: ADEM-3173-MaestroP | I9: =Tabla1[[#This Row],[Nombre Curso]]&" - "&Tabla1[[#This Row],[Semestre]]&"-"&Tabla1[[#This Row],[NRC]] -> Emprendimiento Nivel Básico - 202650-51283 | J9: =E9&D9&"-"&C9 -> ADEM-3173-202650-51283 | K9: =_xlfn.XLOOKUP(Tabla1[[#This Row],[CodMaestro]],UnidadesOrganizaciones!D:D,UnidadesOrganizaciones!Q:Q,"***") -> 38966 | L9: =_xlfn.XLOOKUP(TEXT(Tabla1[[#This Row],[Semestre]],"######"),'CursosBS'!E:E,'CursosBS'!A:A,"***") -> 77362 | M9: =_xlfn.XLOOKUP(Tabla1[[#This Row],[CodCursoOferta]],'CursosBS'!E:E,'CursosBS'!A:A,"*NoExiste*") -> *NoExiste* | N9: ="https://virtual.upb.edu.co/d2l/home/"&Tabla1[[#This Row],[IDCURSO]] -> https://virtual.upb.edu.co/d2l/home/*NoExiste*
A10: =_xlfn.XLOOKUP(Tabla1[[#This Row],[CodMaestro]],UnidadesOrganizaciones!D:D,UnidadesOrganizaciones!L:L,"***") -> CVFC | B10: Emprendimiento Nivel Básico | C10: 51284 | D10: 202650 | E10: =_xlfn.TEXTBEFORE(H10,"MaestroP") -> ADEM-3173- | F10: =_xlfn.XLOOKUP(Tabla1[[#This Row],[CodMaestro]],UnidadesOrganizaciones!D:D,UnidadesOrganizaciones!C:C,"***") -> Emprendimiento Nivel Básico -QMMaestroP(R) | G10: =LEFT(F10,FIND(" -",F10&" -")-1) -> Emprendimiento Nivel Básico | H10: ADEM-3173-MaestroP | I10: =Tabla1[[#This Row],[Nombre Curso]]&" - "&Tabla1[[#This Row],[Semestre]]&"-"&Tabla1[[#This Row],[NRC]] -> Emprendimiento Nivel Básico - 202650-51284 | J10: =E10&D10&"-"&C10 -> ADEM-3173-202650-51284 | K10: =_xlfn.XLOOKUP(Tabla1[[#This Row],[CodMaestro]],UnidadesOrganizaciones!D:D,UnidadesOrganizaciones!Q:Q,"***") -> 38966 | L10: =_xlfn.XLOOKUP(TEXT(Tabla1[[#This Row],[Semestre]],"######"),'CursosBS'!E:E,'CursosBS'!A:A,"***") -> 77362 | M10: =_xlfn.XLOOKUP(Tabla1[[#This Row],[CodCursoOferta]],'CursosBS'!E:E,'CursosBS'!A:A,"*NoExiste*") -> *NoExiste* | N10: ="https://virtual.upb.edu.co/d2l/home/"&Tabla1[[#This Row],[IDCURSO]] -> https://virtual.upb.edu.co/d2l/home/*NoExiste*
A11: =_xlfn.XLOOKUP(Tabla1[[#This Row],[CodMaestro]],UnidadesOrganizaciones!D:D,UnidadesOrganizaciones!L:L,"***") -> CVFC | B11: Emprendimiento Nivel Básico | C11: 51285 | D11: 202650 | E11: =_xlfn.TEXTBEFORE(H11,"MaestroP") -> ADEM-3173- | F11: =_xlfn.XLOOKUP(Tabla1[[#This Row],[CodMaestro]],UnidadesOrganizaciones!D:D,UnidadesOrganizaciones!C:C,"***") -> Emprendimiento Nivel Básico -QMMaestroP(R) | G11: =LEFT(F11,FIND(" -",F11&" -")-1) -> Emprendimiento Nivel Básico | H11: ADEM-3173-MaestroP | I11: =Tabla1[[#This Row],[Nombre Curso]]&" - "&Tabla1[[#This Row],[Semestre]]&"-"&Tabla1[[#This Row],[NRC]] -> Emprendimiento Nivel Básico - 202650-51285 | J11: =E11&D11&"-"&C11 -> ADEM-3173-202650-51285 | K11: =_xlfn.XLOOKUP(Tabla1[[#This Row],[CodMaestro]],UnidadesOrganizaciones!D:D,UnidadesOrganizaciones!Q:Q,"***") -> 38966 | L11: =_xlfn.XLOOKUP(TEXT(Tabla1[[#This Row],[Semestre]],"######"),'CursosBS'!E:E,'CursosBS'!A:A,"***") -> 77362 | M11: =_xlfn.XLOOKUP(Tabla1[[#This Row],[CodCursoOferta]],'CursosBS'!E:E,'CursosBS'!A:A,"*NoExiste*") -> *NoExiste* | N11: ="https://virtual.upb.edu.co/d2l/home/"&Tabla1[[#This Row],[IDCURSO]] -> https://virtual.upb.edu.co/d2l/home/*NoExiste*
A12: =_xlfn.XLOOKUP(Tabla1[[#This Row],[CodMaestro]],UnidadesOrganizaciones!D:D,UnidadesOrganizaciones!L:L,"***") -> CVFC | B12: Emprendimiento Nivel Básico | C12: 51286 | D12: 202650 | E12: =_xlfn.TEXTBEFORE(H12,"MaestroP") -> ADEM-3173- | F12: =_xlfn.XLOOKUP(Tabla1[[#This Row],[CodMaestro]],UnidadesOrganizaciones!D:D,UnidadesOrganizaciones!C:C,"***") -> Emprendimiento Nivel Básico -QMMaestroP(R) | G12: =LEFT(F12,FIND(" -",F12&" -")-1) -> Emprendimiento Nivel Básico | H12: ADEM-3173-MaestroP | I12: =Tabla1[[#This Row],[Nombre Curso]]&" - "&Tabla1[[#This Row],[Semestre]]&"-"&Tabla1[[#This Row],[NRC]] -> Emprendimiento Nivel Básico - 202650-51286 | J12: =E12&D12&"-"&C12 -> ADEM-3173-202650-51286 | K12: =_xlfn.XLOOKUP(Tabla1[[#This Row],[CodMaestro]],UnidadesOrganizaciones!D:D,UnidadesOrganizaciones!Q:Q,"***") -> 38966 | L12: =_xlfn.XLOOKUP(TEXT(Tabla1[[#This Row],[Semestre]],"######"),'CursosBS'!E:E,'CursosBS'!A:A,"***") -> 77362 | M12: =_xlfn.XLOOKUP(Tabla1[[#This Row],[CodCursoOferta]],'CursosBS'!E:E,'CursosBS'!A:A,"*NoExiste*") -> *NoExiste* | N12: ="https://virtual.upb.edu.co/d2l/home/"&Tabla1[[#This Row],[IDCURSO]] -> https://virtual.upb.edu.co/d2l/home/*NoExiste*
A13: =_xlfn.XLOOKUP(Tabla1[[#This Row],[CodMaestro]],UnidadesOrganizaciones!D:D,UnidadesOrganizaciones!L:L,"***") -> CVFC | B13: Emprendimiento Nivel Básico | C13: 51287 | D13: 202650 | E13: =_xlfn.TEXTBEFORE(H13,"MaestroP") -> ADEM-3173- | F13: =_xlfn.XLOOKUP(Tabla1[[#This Row],[CodMaestro]],UnidadesOrganizaciones!D:D,UnidadesOrganizaciones!C:C,"***") -> Emprendimiento Nivel Básico -QMMaestroP(R) | G13: =LEFT(F13,FIND(" -",F13&" -")-1) -> Emprendimiento Nivel Básico | H13: ADEM-3173-MaestroP | I13: =Tabla1[[#This Row],[Nombre Curso]]&" - "&Tabla1[[#This Row],[Semestre]]&"-"&Tabla1[[#This Row],[NRC]] -> Emprendimiento Nivel Básico - 202650-51287 | J13: =E13&D13&"-"&C13 -> ADEM-3173-202650-51287 | K13: =_xlfn.XLOOKUP(Tabla1[[#This Row],[CodMaestro]],UnidadesOrganizaciones!D:D,UnidadesOrganizaciones!Q:Q,"***") -> 38966 | L13: =_xlfn.XLOOKUP(TEXT(Tabla1[[#This Row],[Semestre]],"######"),'CursosBS'!E:E,'CursosBS'!A:A,"***") -> 77362 | M13: =_xlfn.XLOOKUP(Tabla1[[#This Row],[CodCursoOferta]],'CursosBS'!E:E,'CursosBS'!A:A,"*NoExiste*") -> *NoExiste* | N13: ="https://virtual.upb.edu.co/d2l/home/"&Tabla1[[#This Row],[IDCURSO]] -> https://virtual.upb.edu.co/d2l/home/*NoExiste*
... A15: =_xlfn.XLOOKUP(Tabla1[[#This Row],[CodMaestro]],UnidadesOrganizaciones!D:D,UnidadesOrganizaciones!L:L,"***") -> CVFC | B15: Emprendimiento Nivel Básico | C15: 51289 | D15: 202650 | E15: =_xlfn.TEXTBEFORE(H15,"MaestroP") -> ADEM-3173- | F15: =_xlfn.XLOOKUP(Tabla1[[#This Row],[CodMaestro]],UnidadesOrganizaciones!D:D,UnidadesOrganizaciones!C:C,"***") -> Emprendimiento Nivel Básico -QMMaestroP(R) | G15: =LEFT(F15,FIND(" -",F15&" -")-1) -> Emprendimiento Nivel Básico | H15: ADEM-3173-MaestroP | I15: =Tabla1[[#This Row],[Nombre Curso]]&" - "&Tabla1[[#This Row],[Semestre]]&"-"&Tabla1[[#This Row],[NRC]] -> Emprendimiento Nivel Básico - 202650-51289 | J15: =E15&D15&"-"&C15 -> ADEM-3173-202650-51289 | K15: =_xlfn.XLOOKUP(Tabla1[[#This Row],[CodMaestro]],UnidadesOrganizaciones!D:D,UnidadesOrganizaciones!Q:Q,"***") -> 38966 | L15: =_xlfn.XLOOKUP(TEXT(Tabla1[[#This Row],[Semestre]],"######"),'CursosBS'!E:E,'CursosBS'!A:A,"***") -> 77362 | M15: =_xlfn.XLOOKUP(Tabla1[[#This Row],[CodCursoOferta]],'CursosBS'!E:E,'CursosBS'!A:A,"*NoExiste*") -> *NoExiste* | N15: ="https://virtual.upb.edu.co/d2l/home/"&Tabla1[[#This Row],[IDCURSO]] -> https://virtual.upb.edu.co/d2l/home/*NoExiste*

Sheet UnidadesOrganizaciones
A1: CourseOfferingId | B1: CourseOfferingType | C1: CourseOfferingName | D1: CourseOfferingCode | E1: OrganizationId | F1: OrganizationTypeId | G1: OrganizationType | H1: OrganizationName | I1: NivelId | J1: NivelType | K1: NivelName | L1: NivelCode | M1: ProgramaDepartamentoId | N1: ProgramaDepartamentoType | O1: ProgramaDepartamentoName | P1: ProgramaDepartamentoCode | Q1: TemplateId | R1: TemplateType | S1: TemplateName | T1: TemplateCode | U1: SemesterCode
A2: 6610 | B2: Course Offering | C2: Brightspace Training Shell | D2: TEMP_co-training-course-d2l_201810_ | E2: 6606 | F2: 1 | G2: Organization | H2: UPBVirtual | I2: 29013 | J2: Nivel | K2: Campus Virtual Extensión | L2: CVFC | M2: 34493 | N2: Programa - Departamento | O2: CVFC- UPB Virtual | P2: CVFC-UPBV | Q2: 6608 | R2: Course Template | S2: Training courses container | T2: TEMP_ct_training_d2l
A3: 6615 | B3: Course Offering | C3: Brightspace Bulk Create | D3: TEMP_utils-BCC-d2l_201810_ | E3: 6606 | F3: 1 | G3: Organization | H3: UPBVirtual | I3: 29013 | J3: Nivel | K3: Campus Virtual Extensión | L3: CVFC | M3: 34493 | N3: Programa - Departamento | O3: CVFC- UPB Virtual | P3: CVFC-UPBV | Q3: 6614 | R3: Course Template | S3: Bulk tools container | T3: Temp_ct_bulktools_d2l
A4: 6616 | B4: Course Offering | C4: Brightspace Bulk Export | D4: TEMP_utils-BCE-D2L_201810_ | E4: 6606 | F4: 1 | G4: Organization | H4: UPBVirtual | I4: 29013 | J4: Nivel | K4: Campus Virtual Extensión | L4: CVFC | M4: 34493 | N4: Programa - Departamento | O4: CVFC- UPB Virtual | P4: CVFC-UPBV | Q4: 6614 | R4: Course Template | S4: Bulk tools container | T4: Temp_ct_bulktools_d2l
A5: 6626 | B5: Course Offering | C5: Sandbox - Demo.Instructor | D5: TEMP_demo-instructor.sb_201810_ | E5: 6606 | F5: 1 | G5: Organization | H5: UPBVirtual | I5: 29013 | J5: Nivel | K5: Campus Virtual Extensión | L5: CVFC | M5: 34493 | N5: Programa - Departamento | O5: CVFC- UPB Virtual | P5: CVFC-UPBV | Q5: 6625 | R5: Course Template | S5: Brightspace Sandboxes container | T5: TEMP_ct_brightspace_sandboxes_sb
A6: 6633 | B6: Course Offering | C6: Brightspace Bulk Copy | D6: TEMP_utils-CCB-D2L_201810_ | E6: 6606 | F6: 1 | G6: Organization | H6: UPBVirtual | I6: 29013 | J6: Nivel | K6: Campus Virtual Extensión | L6: CVFC | M6: 34493 | N6: Programa - Departamento | O6: CVFC- UPB Virtual | P6: CVFC-UPBV | Q6: 6614 | R6: Course Template | S6: Bulk tools container | T6: Temp_ct_bulktools_d2l
A7: 6634 | B7: Course Offering | C7: Brightspace Admin and Data Central | D7: TEMP_admin-central-d2l_201810_ | E7: 6606 | F7: 1 | G7: Organization | H7: UPBVirtual | I7: 29013 | J7: Nivel | K7: Campus Virtual Extensión | L7: CVFC | M7: 34493 | N7: Programa - Departamento | O7: CVFC- UPB Virtual | P7: CVFC-UPBV | Q7: 6628 | R7: Course Template | S7: Implementation courses container | T7: TEMP_ct_implementation_d2l
A8: 6636 | B8: Course Offering | C8: Brightspace Implementation Center | D8: TEMP_Brightspace-101-d2l_201810_ | E8: 6606 | F8: 1 | G8: Organization | H8: UPBVirtual | I8: 29013 | J8: Nivel | K8: Campus Virtual Extensión | L8: CVFC | M8: 34493 | N8: Programa - Departamento | O8: CVFC- UPB Virtual | P8: CVFC-UPBV | Q8: 6628 | R8: Course Template | S8: Implementation courses container | T8: TEMP_ct_implementation_d2l
A9: 6642 | B9: Course Offering | C9: Brightspace Sample - Activity Feed | D9: TEMP_activityfeed-d2l-sb_201810_ | E9: 6606 | F9: 1 | G9: Organization | H9: UPBVirtual | I9: 29013 | J9: Nivel | K9: Campus Virtual Extensión | L9: CVFC | M9: 34493 | N9: Programa - Departamento | O9: CVFC- UPB Virtual | P9: CVFC-UPBV | Q9: 6625 | R9: Course Template | S9: Brightspace Sandboxes container | T9: TEMP_ct_brightspace_sandboxes_sb
A10: 6643 | B10: Course Offering | C10: Brightspace Sample - Image Based Nav | D10: TEMP_imagebasednav-d2l-sb_201810_ | E10: 6606 | F10: 1 | G10: Organization | H10: UPBVirtual | I10: 29013 | J10: Nivel | K10: Campus Virtual Extensión | L10: CVFC | M10: 34493 | N10: Programa - Departamento | O10: CVFC- UPB Virtual | P10: CVFC-UPBV | Q10: 6625 | R10: Course Template | S10: Brightspace Sandboxes container | T10: TEMP_ct_brightspace_sandboxes_sb
A11: 6645 | B11: Course Offering | C11: Brightspace Sample - Lessons | D11: TEMP_Lessons-d2l-sb_201810_ | E11: 6606 | F11: 1 | G11: Organization | H11: UPBVirtual | I11: 29013 | J11: Nivel | K11: Campus Virtual Extensión | L11: CVFC | M11: 34493 | N11: Programa - Departamento | O11: CVFC- UPB Virtual | P11: CVFC-UPBV | Q11: 6644 | R11: Course Template | S11: Brightspace Lessons Sandbox Container | T11: TEMP_lessons_sb_ct
A12: 6658 | B12: Course Offering | C12: e-moderación 50815_201850 | D12: VROb_eModeracion_201850_50815 | E12: 6606 | F12: 1 | G12: Organization | H12: UPBVirtual | I12: 29013 | J12: Nivel | K12: Campus Virtual Extensión | L12: CVFC | M12: 34493 | N12: Programa - Departamento | O12: CVFC- UPB Virtual | P12: CVFC-UPBV | Q12: 34494 | R12: Course Template | S12: Diplomado en Educación Virtual | T12: CVFC-MXEO | U12: 201850
A13: 6663 | B13: Course Offering | C13: English | D13: TEMP_BLENDED_2018_ | E13: 6606 | F13: 1 | G13: Organization | H13: UPBVirtual | I13: 29013 | J13: Nivel | K13: Campus Virtual Extensión | L13: CVFC | M13: 34493 | N13: Programa - Departamento | O13: CVFC- UPB Virtual | P13: CVFC-UPBV | Q13: 6659 | R13: Course Template | S13: Blended Course Template | T13: temp_blend
A14: 6665 | B14: Course Offering | C14: Introduction to CBE | D14: TEMP_ONLINE_2018_ | E14: 6606 | F14: 1 | G14: Organization | H14: UPBVirtual | I14: 29013 | J14: Nivel | K14: Campus Virtual Extensión | L14: CVFC | M14: 34493 | N14: Programa - Departamento | O14: CVFC- UPB Virtual | P14: CVFC-UPBV | Q14: 6664 | R14: Course Template | S14: Online Course Template | T14: temp_online
A15: 6680 | B15: Course Offering | C15: Biología humana | D15: TEMP_biologiahumana_2018_ | E15: 6606 | F15: 1 | G15: Organization | H15: UPBVirtual | I15: 29013 | J15: Nivel | K15: Campus Virtual Extensión | L15: CVFC | M15: 34493 | N15: Programa - Departamento | O15: CVFC- UPB Virtual | P15: CVFC-UPBV | Q15: 6679 | R15: Course Template | S15: Template Biología humana | T15: template_biologiahumana
A16: 6694 | B16: Course Offering | C16: Estadista Aplicada | D16: VSOb_m6-est-apli_201810_ | E16: 6606 | F16: 1 | G16: Organization | H16: UPBVirtual | I16: 29013 | J16: Nivel | K16: Campus Virtual Extensión | L16: CVFC | M16: 34493 | N16: Programa - Departamento | O16: CVFC- UPB Virtual | P16: CVFC-UPBV | Q16: 6693 | R16: Course Template | S16: template_m6_est_apli | T16: template_m6_est_apli
A17: 6748 | B17: Course Offering | C17: e-Moderación 50816_201850 | D17: VROb_eModeracion_201850_50816 | E17: 6606 | F17: 1 | G17: Organization | H17: UPBVirtual | I17: 29013 | J17: Nivel | K17: Campus Virtual Extensión | L17: CVFC | M17: 34493 | N17: Programa - Departamento | O17: CVFC- UPB Virtual | P17: CVFC-UPBV | Q17: 34494 | R17: Course Template | S17: Diplomado en Educación Virtual | T17: CVFC-MXEO | U17: 201850
A18: 6792 | B18: Course Offering | C18: Curso Modelo 1 | D18: TEMP_Curso Modelo 1_2018_ | E18: 6606 | F18: 1 | G18: Organization | H18: UPBVirtual | I18: 29013 | J18: Nivel | K18: Campus Virtual Extensión | L18: CVFC | M18: 34493 | N18: Programa - Departamento | O18: CVFC- UPB Virtual | P18: CVFC-UPBV | Q18: 6791 | R18: Course Template | S18: Curso Modelo 1 | T18: Curso Modelo 1
A19: 6794 | B19: Course Offering | C19: Curso Modelo 2 | D19: TEMP_Curso Modelo 2_2018_ | E19: 6606 | F19: 1 | G19: Organization | H19: UPBVirtual | I19: 29013 | J19: Nivel | K19: Campus Virtual Extensión | L19: CVFC | M19: 34493 | N19: Programa - Departamento | O19: CVFC- UPB Virtual | P19: CVFC-UPBV | Q19: 6793 | R19: Course Template | S19: Curso modelo 2 | T19: Curso modelo 2
A20: 6796 | B20: Course Offering | C20: Curso Modelo 3 | D20: TEMP_CursoModelo3_2018_ | E20: 6606 | F20: 1 | G20: Organization | H20: UPBVirtual | I20: 29013 | J20: Nivel | K20: Campus Virtual Extensión | L20: CVFC | M20: 34493 | N20: Programa - Departamento | O20: CVFC- UPB Virtual | P20: CVFC-UPBV | Q20: 6795 | R20: Course Template | S20: Curso Modelo 3 | T20: Curso Modelo 3
A21: 6886 | B21: Course Offering | C21: Ensayos Sergio 2 con plantilla | D21: Temp_SZA-ensayo2_201810_NRC | E21: 6606 | F21: 1 | G21: Organization | H21: UPBVirtual | I21: 29013 | J21: Nivel | K21: Campus Virtual Extensión | L21: CVFC | M21: 34493 | N21: Programa - Departamento | O21: CVFC- UPB Virtual | P21: CVFC-UPBV | Q21: 6884 | R21: Course Template | S21: PLANTILLA Ensayo | T21: PLANTILLAEnsayo
A22: 6889 | B22: Course Offering | C22: EcologiaDigital | D22: TEMP_EcologiaDigital_2018_ | E22: 6606 | F22: 1 | G22: Organization | H22: UPBVirtual | I22: 29013 | J22: Nivel | K22: Campus Virtual Extensión | L22: CVFC | M22: 34493 | N22: Programa - Departamento | O22: CVFC- UPB Virtual | P22: CVFC-UPBV | Q22: 6884 | R22: Course Template | S22: PLANTILLA Ensayo | T22: PLANTILLAEnsayo
A23: 6893 | B23: Course Offering | C23: LE + eP + LOR | D23: TEMP_co-capacitacion-d2l_201810_ | E23: 6606 | F23: 1 | G23: Organization | H23: UPBVirtual | I23: 29013 | J23: Nivel | K23: Campus Virtual Extensión | L23: CVFC | M23: 34493 | N23: Programa - Departamento | O23: CVFC- UPB Virtual | P23: CVFC-UPBV | Q23: 6892 | R23: Course Template | S23: Capacitaciones | T23: TEMP_capacita_d2l
A24: 6900 | B24: Course Offering | C24: Standardized English Test (Pregrado Med) | D24: PDOb_StandardizedEnglishTestPreMed_201950_ | E24: 6606 | F24: 1 | G24: Organization | H24: UPBVirtual | I24: 29013 | J24: Nivel | K24: Campus Virtual Extensión | L24: CVFC | M24: 35301 | N24: Programa - Departamento | O24: CVFC- Centro Lenguas-Med | P24: CVFC-MCLE | Q24: 6899 | R24: Course Template | S24: Plan_cursos_FCCentroLenguas | T24: MJLE | U24: 201950
A25: 6901 | B25: Course Offering | C25: Capacitación Administradores | D25: TEMP_CapacAdmores_2018_ | E25: 6606 | F25: 1 | G25: Organization | H25: UPBVirtual | I25: 29013 | J25: Nivel | K25: Campus Virtual Extensión | L25: CVFC | M25: 34493 | N25: Programa - Departamento | O25: CVFC- UPB Virtual | P25: CVFC-UPBV | Q25: 6608 | R25: Course Template | S25: Training courses container | T25: TEMP_ct_training_d2l
A26: 6903 | B26: Course Offering | C26: Curso_ejemplo_scorm - ADAMS | D26: TEMP_Curso-Ejemplo-Scorm_201810_ | E26: 6606 | F26: 1 | G26: Organization | H26: UPBVirtual | I26: 29013 | J26: Nivel | K26: Campus Virtual Extensión | L26: CVFC | M26: 34493 | N26: Programa - Departamento | O26: CVFC- UPB Virtual | P26: CVFC-UPBV | Q26: 6902 | R26: Course Template | S26: temp_curso_scorm | T26: temp_curso_scorm
A27: 6905 | B27: Course Offering | C27: Ejemplo con plantilla 01 | D27: TEMP_Ejemplo_201810_NRC | E27: 6606 | F27: 1 | G27: Organization | H27: UPBVirtual | I27: 29013 | J27: Nivel | K27: Campus Virtual Extensión | L27: CVFC | M27: 34493 | N27: Programa - Departamento | O27: CVFC- UPB Virtual | P27: CVFC-UPBV | Q27: 7208 | R27: Course Template | S27: Plan_ProgramaCursosEstudio | T27: Plan_ProgramaCursosEstudio
A28: 6924 | B28: Course Offering | C28: E-moderación 51244_201850 | D28: VROb_eModeracion_201850_51244 | E28: 6606 | F28: 1 | G28: Organization | H28: UPBVirtual | I28: 29013 | J28: Nivel | K28: Campus Virtual Extensión | L28: CVFC | M28: 34493 | N28: Programa - Departamento | O28: CVFC- UPB Virtual | P28: CVFC-UPBV | Q28: 34494 | R28: Course Template | S28: Diplomado en Educación Virtual | T28: CVFC-MXEO | U28: 201850
A29: 6925 | B29: Course Offering | C29: E-moderación 51243_201850 | D29: VROb_eModeracion_201850_51243 | E29: 6606 | F29: 1 | G29: Organization | H29: UPBVirtual | I29: 29013 | J29: Nivel | K29: Campus Virtual Extensión | L29: CVFC | M29: 34493 | N29: Programa - Departamento | O29: CVFC- UPB Virtual | P29: CVFC-UPBV | Q29: 34494 | R29: Course Template | S29: Diplomado en Educación Virtual | T29: CVFC-MXEO | U29: 201850
A30: 7081 | B30: Course Offering | C30: ECPD-Narrativas convergentes - **Copia20230203** | D30: VECD-5557 0048-Copia20230203 | E30: 6606 | F30: 1 | G30: Organization | H30: UPBVirtual | I30: 29010 | J30: Nivel | K30: Campus Virtual Posgrados | L30: CVFA | M30: 35347 | N30: Programa - Departamento | O30: CVFA-VPCS-Ciencias Sociales | P30: CVFA-VPCS | Q30: 6904 | R30: Course Template | S30: CVFA-VECD- Esp.Comun y Period Digital-Virt | T30: CVFA-VECD | U30: ControlVersion
A31: 7110 | B31: Course Offering | C31: ECPD - Coordinación de la especialización | D31: PDOb_ECPDCoordEspecia_2023_ | E31: 6606 | F31: 1 | G31: Organization | H31: UPBVirtual | I31: 29010 | J31: Nivel | K31: Campus Virtual Posgrados | L31: CVFA | M31: 35347 | N31: Programa - Departamento | O31: CVFA-VPCS-Ciencias Sociales | P31: CVFA-VPCS | Q31: 6904 | R31: Course Template | S31: CVFA-VECD- Esp.Comun y Period Digital-Virt | T31: CVFA-VECD | U31: CoordProgramas
A32: 7146 | B32: Course Offering | C32: Legislación de Infancia y Adolescencia_**NO USAR**-MaestroV | D32: VROb_CFCFDLegInfAdol_201841_-MaestroV | E32: 6606 | F32: 1 | G32: Organization | H32: UPBVirtual | I32: 29013 | J32: Nivel | K32: Campus Virtual Extensión | L32: CVFC | M32: 35321 | N32: Programa - Departamento | O32: CVFC- Esc. Derecho Ciencias Políticas-Med | P32: CVFC-MD | Q32: 7122 | R32: Course Template | S32: FC Ciencias Políticas-Med | T32: FC-MCPO | U32: ControlVersion
A33: 7158 | B33: Course Offering | C33: BIOLOGÍA DE LA CONSERVACIÓN - HTMaestroC | D33: 9936-2013-MaestroC | E33: 6606 | F33: 1 | G33: Organization | H33: UPBVirtual | I33: 29010 | J33: Nivel | K33: Campus Virtual Posgrados | L33: CVFA | M33: 35352 | N33: Programa - Departamento | O33: CVFA-BI-Ingeniería-Bga | P33: CVFA-BI | Q33: 7134 | R33: Course Template | S33: CVFA-VEPV- Esp. Preser y Cons R Natu-Virt | T33: CVFA-VEPV | U33: CMaestros
A34: 7163 | B34: Course Offering | C34: ECOSISTEMAS ESTRATÉGICOS Y AREAS PROTEGIDAS - HTMaestroC | D34: 9936-2015-MaestroC | E34: 6606 | F34: 1 | G34: Organization | H34: UPBVirtual | I34: 29010 | J34: Nivel | K34: Campus Virtual Posgrados | L34: CVFA | M34: 35352 | N34: Programa - Departamento | O34: CVFA-BI-Ingeniería-Bga | P34: CVFA-BI | Q34: 7134 | R34: Course Template | S34: CVFA-VEPV- Esp. Preser y Cons R Natu-Virt | T34: CVFA-VEPV | U34: CMaestros
A35: 7169 | B35: Course Offering | C35: RESTAURACIÓN Y ECOSISTEMAS -HTMaestroC | D35: CTAM-0102-MaestroC | E35: 6606 | F35: 1 | G35: Organization | H35: UPBVirtual | I35: 29010 | J35: Nivel | K35: Campus Virtual Posgrados | L35: CVFA | M35: 35352 | N35: Programa - Departamento | O35: CVFA-BI-Ingeniería-Bga | P35: CVFA-BI | Q35: 7134 | R35: Course Template | S35: CVFA-VEPV- Esp. Preser y Cons R Natu-Virt | T35: CVFA-VEPV | U35: CMaestros
A36: 7181 | B36: Course Offering | C36: GESTIÓN DE CALIDAD Y ADQUISICIONES - HTMaestroC | D36: 8821-2013-MaestroC | E36: 6606 | F36: 1 | G36: Organization | H36: UPBVirtual | I36: 29010 | J36: Nivel | K36: Campus Virtual Posgrados | L36: CVFA | M36: 35352 | N36: Programa - Departamento | O36: CVFA-BI-Ingeniería-Bga | P36: CVFA-BI | Q36: 6691 | R36: Course Template | S36: CVFA-VEGP- Esp. Gestión de Proyectos-Virt | T36: CVFA-VEGP | U36: CMaestros
A37: 7182 | B37: Course Offering | C37: ECONOMÍA AMBIENTAL -MaestroV | D37: 9936-2011-MaestroV | E37: 6606 | F37: 1 | G37: Organization | H37: UPBVirtual | I37: 29010 | J37: Nivel | K37: Campus Virtual Posgrados | L37: CVFA | M37: 35352 | N37: Programa - Departamento | O37: CVFA-BI-Ingeniería-Bga | P37: CVFA-BI | Q37: 7134 | R37: Course Template | S37: CVFA-VEPV- Esp. Preser y Cons R Natu-Virt | T37: CVFA-VEPV | U37: ControlVersion
A38: 7183 | B38: Course Offering | C38: EPRECORENA-Normatividad Ambienta- HTMaestroV | D38: VEPV-CJDL-0075-MaestroV | E38: 6606 | F38: 1 | G38: Organization | H38: UPBVirtual | I38: 29010 | J38: Nivel | K38: Campus Virtual Posgrados | L38: CVFA | M38: 35352 | N38: Programa - Departamento | O38: CVFA-BI-Ingeniería-Bga | P38: CVFA-BI | Q38: 7134 | R38: Course Template | S38: CVFA-VEPV- Esp. Preser y Cons R Natu-Virt | T38: CVFA-VEPV | U38: ControlVersion
A39: 7185 | B39: Course Offering | C39: FORMULACIÓN Y EVALUACIÓN DE PROYECTOS AMBIENTALES - HTMaestroC | D39: 9936-2014-MaestroC | E39: 6606 | F39: 1 | G39: Organization | H39: UPBVirtual | I39: 29010 | J39: Nivel | K39: Campus Virtual Posgrados | L39: CVFA | M39: 35352 | N39: Programa - Departamento | O39: CVFA-BI-Ingeniería-Bga | P39: CVFA-BI | Q39: 7134 | R39: Course Template | S39: CVFA-VEPV- Esp. Preser y Cons R Natu-Virt | T39: CVFA-VEPV | U39: CMaestros
... A41: 7194 | B41: Course Offering | C41: GESTIÓN ESTRATÉGICA -MaestroC | D41: CEOE-0321-MaestroC | E41: 6606 | F41: 1 | G41: Organization | H41: UPBVirtual | I41: 29010 | J41: Nivel | K41: Campus Virtual Posgrados | L41: CVFA | M41: 35352 | N41: Programa - Departamento | O41: CVFA-BI-Ingeniería-Bga | P41: CVFA-BI | Q41: 6691 | R41: Course Template | S41: CVFA-VEGP- Esp. Gestión de Proyectos-Virt | T41: CVFA-VEGP | U41: CMaestros
A42: 7197 | B42: Course Offering | C42: InnovaTIC Audacity | D42: VREl_InnovaTIC Audacity_201850_NRC | E42: 6606 | F42: 1 | G42: Organization | H42: UPBVirtual | I42: 29013 | J42: Nivel | K42: Campus Virtual Extensión | L42: CVFC | M42: 34493 | N42: Programa - Departamento | O42: CVFC- UPB Virtual | P42: CVFC-UPBV | Q42: 7196 | R42: Course Template | S42: Plan_cursos_Innovatic | T42: Plan_cursos_Innovatic
A43: 7198 | B43: Course Offering | C43: InnovaTIC_Canva | D43: VREl_InnovaTICCanva_201850_NRC | E43: 6606 | F43: 1 | G43: Organization | H43: UPBVirtual | I43: 29013 | J43: Nivel | K43: Campus Virtual Extensión | L43: CVFC | M43: 34493 | N43: Programa - Departamento | O43: CVFC- UPB Virtual | P43: CVFC-UPBV | Q43: 7196 | R43: Course Template | S43: Plan_cursos_Innovatic | T43: Plan_cursos_Innovatic
A44: 7199 | B44: Course Offering | C44: VREl_InnovaTIC LucidChart | D44: VREl_InnovaTIC LucidChart_201850_NRC | E44: 6606 | F44: 1 | G44: Organization | H44: UPBVirtual | I44: 29013 | J44: Nivel | K44: Campus Virtual Extensión | L44: CVFC | M44: 34493 | N44: Programa - Departamento | O44: CVFC- UPB Virtual | P44: CVFC-UPBV | Q44: 7196 | R44: Course Template | S44: Plan_cursos_Innovatic | T44: Plan_cursos_Innovatic
A45: 7209 | B45: Course Offering | C45: Curso prueba Sergio 01 | D45: Temp_CursoPruebaSergio01_2018_ | E45: 6606 | F45: 1 | G45: Organization | H45: UPBVirtual | I45: 29013 | J45: Nivel | K45: Campus Virtual Extensión | L45: CVFC | M45: 34493 | N45: Programa - Departamento | O45: CVFC- UPB Virtual | P45: CVFC-UPBV | Q45: 7208 | R45: Course Template | S45: Plan_ProgramaCursosEstudio | T45: Plan_ProgramaCursosEstudio
A46: 7210 | B46: Course Offering | C46: Curso prueba Sergio 02 | D46: Temp_CursoPruebaSergio02_2018_ | E46: 6606 | F46: 1 | G46: Organization | H46: UPBVirtual | I46: 29013 | J46: Nivel | K46: Campus Virtual Extensión | L46: CVFC | M46: 34493 | N46: Programa - Departamento | O46: CVFC- UPB Virtual | P46: CVFC-UPBV | Q46: 7208 | R46: Course Template | S46: Plan_ProgramaCursosEstudio | T46: Plan_ProgramaCursosEstudio
A47: 7213 | B47: Course Offering | C47: Curso Prototipo01 | D47: PROT_CursoPrototipo01_2018_ | E47: 6606 | F47: 1 | G47: Organization | H47: UPBVirtual | I47: 29013 | J47: Nivel | K47: Campus Virtual Extensión | L47: CVFC | M47: 34493 | N47: Programa - Departamento | O47: CVFC- UPB Virtual | P47: CVFC-UPBV | Q47: 7208 | R47: Course Template | S47: Plan_ProgramaCursosEstudio | T47: Plan_ProgramaCursosEstudio
A48: 7218 | B48: Course Offering | C48: (Viejo)Diplomado Control de Inventarios y Almacenamiento | D48: EDOb_ViejoDiploContInveAlma_201850_51438 | E48: 6606 | F48: 1 | G48: Organization | H48: UPBVirtual | I48: 29013 | J48: Nivel | K48: Campus Virtual Extensión | L48: CVFC | M48: 35325 | N48: Programa - Departamento | O48: CVFC- Esc. Ingeniería-Buc | P48: CVFC-BI | Q48: 7217 | R48: Course Template | S48: Plan_DiplIngeBUC | T48: Plan_DiplIngeBUC | U48: 201850
A49: 7223 | B49: Course Offering | C49: Inferencia Regresión y Diseño de Experimentos | D49: TEMP_InfeRegDiseExpe_2018_ | E49: 6606 | F49: 1 | G49: Organization | H49: UPBVirtual | I49: 29013 | J49: Nivel | K49: Campus Virtual Extensión | L49: CVFC | M49: 34493 | N49: Programa - Departamento | O49: CVFC- UPB Virtual | P49: CVFC-UPBV | Q49: 7208 | R49: Course Template | S49: Plan_ProgramaCursosEstudio | T49: Plan_ProgramaCursosEstudio
A50: 7255 | B50: Course Offering | C50: ÉTICA GENERAL - HTMaestroV | D50: 5555-0009-MaestroV | E50: 6606 | F50: 1 | G50: Organization | H50: UPBVirtual | I50: 29006 | J50: Nivel | K50: Campus Virtual Pregrados | L50: CVPR | M50: 35343 | N50: Programa - Departamento | O50: CVPR- Esc. Teología Filosofía y Hum-Med | P50: CVPR-ETFH | Q50: 6992 | R50: Course Template | S50: Centro de Humanidades-Med | T50: CVPR-MJHU | U50: ControlVersion
A51: 7262 | B51: Course Offering | C51: EGE_Competencias de Negociación 201841 Maestro | D51: Competencias-Negociacion-CMaestro | E51: 6606 | F51: 1 | G51: Organization | H51: UPBVirtual | I51: 29010 | J51: Nivel | K51: Campus Virtual Posgrados | L51: CVFA | M51: 35350 | N51: Programa - Departamento | O51: CVFA-ME-Economía,Admon y Negocios-Med | P51: CVFA-ME | Q51: 31821 | R51: Course Template | S51: CVFA-VEGC- Esp en Gerencia-Vir | T51: CVFA-VEGC | U51: CMaestros
A52: 7271 | B52: Course Offering | C52: Curso Taller Karol | D52: TEMP_CursoTallerKarol_2018_ | E52: 6606 | F52: 1 | G52: Organization | H52: UPBVirtual | I52: 29013 | J52: Nivel | K52: Campus Virtual Extensión | L52: CVFC | M52: 34493 | N52: Programa - Departamento | O52: CVFC- UPB Virtual | P52: CVFC-UPBV | Q52: 7208 | R52: Course Template | S52: Plan_ProgramaCursosEstudio | T52: Plan_ProgramaCursosEstudio
A53: 7273 | B53: Course Offering | C53: Curso taller Adriana | D53: TEMP_CursoTallerAdriana_2018_ | E53: 6606 | F53: 1 | G53: Organization | H53: UPBVirtual | I53: 29013 | J53: Nivel | K53: Campus Virtual Extensión | L53: CVFC | M53: 34493 | N53: Programa - Departamento | O53: CVFC- UPB Virtual | P53: CVFC-UPBV | Q53: 7208 | R53: Course Template | S53: Plan_ProgramaCursosEstudio | T53: Plan_ProgramaCursosEstudio
A54: 7277 | B54: Course Offering | C54: Curso Taller Jenny | D54: TEMP_CursoTallerJenny_2018_ | E54: 6606 | F54: 1 | G54: Organization | H54: UPBVirtual | I54: 29013 | J54: Nivel | K54: Campus Virtual Extensión | L54: CVFC | M54: 34493 | N54: Programa - Departamento | O54: CVFC- UPB Virtual | P54: CVFC-UPBV | Q54: 7208 | R54: Course Template | S54: Plan_ProgramaCursosEstudio | T54: Plan_ProgramaCursosEstudio
A55: 7283 | B55: Course Offering | C55: Curso taller MiguelVega 2018 | D55: TEMP_CursoTallerMiguelVega_2018_ | E55: 6606 | F55: 1 | G55: Organization | H55: UPBVirtual | I55: 29013 | J55: Nivel | K55: Campus Virtual Extensión | L55: CVFC | M55: 34493 | N55: Programa - Departamento | O55: CVFC- UPB Virtual | P55: CVFC-UPBV | Q55: 7208 | R55: Course Template | S55: Plan_ProgramaCursosEstudio | T55: Plan_ProgramaCursosEstudio
A56: 7287 | B56: Course Offering | C56: Curso taller2 Ramiro Romero-Prueba | D56: TEMP_CursoTaller2Ramiro_2020_Prueba | E56: 6606 | F56: 1 | G56: Organization | H56: UPBVirtual | I56: 29013 | J56: Nivel | K56: Campus Virtual Extensión | L56: CVFC | M56: 34493 | N56: Programa - Departamento | O56: CVFC- UPB Virtual | P56: CVFC-UPBV | Q56: 7208 | R56: Course Template | S56: Plan_ProgramaCursosEstudio | T56: Plan_ProgramaCursosEstudio
A57: 7289 | B57: Course Offering | C57: Curso taller Luz Adriana | D57: TEMP_Curso taller Luz Adriana_2018_ | E57: 6606 | F57: 1 | G57: Organization | H57: UPBVirtual | I57: 29013 | J57: Nivel | K57: Campus Virtual Extensión | L57: CVFC | M57: 34493 | N57: Programa - Departamento | O57: CVFC- UPB Virtual | P57: CVFC-UPBV | Q57: 7208 | R57: Course Template | S57: Plan_ProgramaCursosEstudio | T57: Plan_ProgramaCursosEstudio
A58: 7306 | B58: Course Offering | C58: e-Moderación ANTERIOR_-MaestroV | D58: VROb_eModeracionANTERIOR_201841-MaestroV | E58: 6606 | F58: 1 | G58: Organization | H58: UPBVirtual | I58: 29013 | J58: Nivel | K58: Campus Virtual Extensión | L58: CVFC | M58: 34493 | N58: Programa - Departamento | O58: CVFC- UPB Virtual | P58: CVFC-UPBV | Q58: 34494 | R58: Course Template | S58: Diplomado en Educación Virtual | T58: CVFC-MXEO | U58: ControlVersion
A59: 7317 | B59: Course Offering | C59: Talleres de formación INNOVATIC UPB Virtual 201850 | D59: VROp_TalleresUPBVirtual_201850_ | E59: 6606 | F59: 1 | G59: Organization | H59: UPBVirtual | I59: 29013 | J59: Nivel | K59: Campus Virtual Extensión | L59: CVFC | M59: 34493 | N59: Programa - Departamento | O59: CVFC- UPB Virtual | P59: CVFC-UPBV | Q59: 7196 | R59: Course Template | S59: Plan_cursos_Innovatic | T59: Plan_cursos_Innovatic | U59: 201850
A60: 7330 | B60: Course Offering | C60: Curso Taller Ramiro | D60: TEMP_CursoTallerRamiro_2018_ | E60: 6606 | F60: 1 | G60: Organization | H60: UPBVirtual | I60: 29013 | J60: Nivel | K60: Campus Virtual Extensión | L60: CVFC | M60: 34493 | N60: Programa - Departamento | O60: CVFC- UPB Virtual | P60: CVFC-UPBV | Q60: 7208 | R60: Course Template | S60: Plan_ProgramaCursosEstudio | T60: Plan_ProgramaCursosEstudio
A61: 7334 | B61: Course Offering | C61: Capacitación BS Maestro _2018 | D61: CROb_CapacitBS_201850_CMaestro | E61: 6606 | F61: 1 | G61: Organization | H61: UPBVirtual | I61: 29013 | J61: Nivel | K61: Campus Virtual Extensión | L61: CVFC | M61: 34493 | N61: Programa - Departamento | O61: CVFC- UPB Virtual | P61: CVFC-UPBV | Q61: 7138 | R61: Course Template | S61: Plan_cursos_FormUPBV | T61: FormUPBV | U61: TEMP_CapUPBVIRTUAL
A62: 7335 | B62: Course Offering | C62: D2L - Visual TOC demo | D62: TEMP_d2lvisualtocdemocourse_2018_ | E62: 6606 | F62: 1 | G62: Organization | H62: UPBVirtual | I62: 29013 | J62: Nivel | K62: Campus Virtual Extensión | L62: CVFC | M62: 34493 | N62: Programa - Departamento | O62: CVFC- UPB Virtual | P62: CVFC-UPBV | Q62: 6625 | R62: Course Template | S62: Brightspace Sandboxes container | T62: TEMP_ct_brightspace_sandboxes_sb
A63: 7336 | B63: Course Offering | C63: Capacitación BS Grupo 01 _2018 | D63: CROb_CapacitBSG01_201850_ | E63: 6606 | F63: 1 | G63: Organization | H63: UPBVirtual | I63: 29013 | J63: Nivel | K63: Campus Virtual Extensión | L63: CVFC | M63: 34493 | N63: Programa - Departamento | O63: CVFC- UPB Virtual | P63: CVFC-UPBV | Q63: 7138 | R63: Course Template | S63: Plan_cursos_FormUPBV | T63: FormUPBV | U63: TEMP_CapUPBVIRTUAL
A64: 7337 | B64: Course Offering | C64: Capacitación BS Grupo 02 _2018 | D64: CROb_CapacitBSG02_201850_ | E64: 6606 | F64: 1 | G64: Organization | H64: UPBVirtual | I64: 29013 | J64: Nivel | K64: Campus Virtual Extensión | L64: CVFC | M64: 34493 | N64: Programa - Departamento | O64: CVFC- UPB Virtual | P64: CVFC-UPBV | Q64: 7138 | R64: Course Template | S64: Plan_cursos_FormUPBV | T64: FormUPBV | U64: TEMP_CapUPBVIRTUAL
A65: 7338 | B65: Course Offering | C65: (Viejo)Arte Moderno -MaestroV | D65: MJHU-UPBM-0001_-MaestroV | E65: 6606 | F65: 1 | G65: Organization | H65: UPBVirtual | I65: 29006 | J65: Nivel | K65: Campus Virtual Pregrados | L65: CVPR | M65: 35343 | N65: Programa - Departamento | O65: CVPR- Esc. Teología Filosofía y Hum-Med | P65: CVPR-ETFH | Q65: 6992 | R65: Course Template | S65: Centro de Humanidades-Med | T65: CVPR-MJHU | U65: ControlVersion
A66: 7339 | B66: Course Offering | C66: DESARROLLO HUMANO Y GLOBALIZACIÓN -MaestroV | D66: 5556-0025-MaestroV | E66: 6606 | F66: 1 | G66: Organization | H66: UPBVirtual | I66: 29006 | J66: Nivel | K66: Campus Virtual Pregrados | L66: CVPR | M66: 35343 | N66: Programa - Departamento | O66: CVPR- Esc. Teología Filosofía y Hum-Med | P66: CVPR-ETFH | Q66: 6992 | R66: Course Template | S66: Centro de Humanidades-Med | T66: CVPR-MJHU | U66: ControlVersion
A67: 7340 | B67: Course Offering | C67: INTRODUCCIÓN A LA LITERATURA -MaestroC | D67: 5564-0009-MaestroC | E67: 6606 | F67: 1 | G67: Organization | H67: UPBVirtual | I67: 29006 | J67: Nivel | K67: Campus Virtual Pregrados | L67: CVPR | M67: 35343 | N67: Programa - Departamento | O67: CVPR- Esc. Teología Filosofía y Hum-Med | P67: CVPR-ETFH | Q67: 6992 | R67: Course Template | S67: Centro de Humanidades-Med | T67: CVPR-MJHU | U67: CMaestros
A68: 7341 | B68: Course Offering | C68: E-moderación 51849_201850 | D68: VROb_eModeracion_201850_51849 | E68: 6606 | F68: 1 | G68: Organization | H68: UPBVirtual | I68: 29013 | J68: Nivel | K68: Campus Virtual Extensión | L68: CVFC | M68: 34493 | N68: Programa - Departamento | O68: CVFC- UPB Virtual | P68: CVFC-UPBV | Q68: 34494 | R68: Course Template | S68: Diplomado en Educación Virtual | T68: CVFC-MXEO | U68: 201850
A69: 7350 | B69: Course Offering | C69: Capacitación BS trabajo social - Docentes _2018 | D69: CROb_CapacitBSTrabajoSocialDoc_201850_ | E69: 6606 | F69: 1 | G69: Organization | H69: UPBVirtual | I69: 29013 | J69: Nivel | K69: Campus Virtual Extensión | L69: CVFC | M69: 34493 | N69: Programa - Departamento | O69: CVFC- UPB Virtual | P69: CVFC-UPBV | Q69: 7138 | R69: Course Template | S69: Plan_cursos_FormUPBV | T69: FormUPBV | U69: TEMP_CapUPBVIRTUAL
A70: 7351 | B70: Course Offering | C70: Capacitación BS trabajo social - Estudiantes _2018 | D70: CROb_CapacitBSTrabajoSocialEst_201850_ | E70: 6606 | F70: 1 | G70: Organization | H70: UPBVirtual | I70: 29013 | J70: Nivel | K70: Campus Virtual Extensión | L70: CVFC | M70: 34493 | N70: Programa - Departamento | O70: CVFC- UPB Virtual | P70: CVFC-UPBV | Q70: 7138 | R70: Course Template | S70: Plan_cursos_FormUPBV | T70: FormUPBV | U70: TEMP_CapUPBVIRTUAL
A71: 7352 | B71: Course Offering | C71: Talleres de formación INNOVATIC UPB Pres 201850 | D71: VDOp_TalleresUPBPres_201850_ | E71: 6606 | F71: 1 | G71: Organization | H71: UPBVirtual | I71: 29013 | J71: Nivel | K71: Campus Virtual Extensión | L71: CVFC | M71: 34493 | N71: Programa - Departamento | O71: CVFC- UPB Virtual | P71: CVFC-UPBV | Q71: 7196 | R71: Course Template | S71: Plan_cursos_Innovatic | T71: Plan_cursos_Innovatic | U71: 201850
A72: 7353 | B72: Course Offering | C72: ARTE DEL RENACIMIENTO -HTMaestroV | D72: 2024-0011-MaestroV | E72: 6606 | F72: 1 | G72: Organization | H72: UPBVirtual | I72: 29006 | J72: Nivel | K72: Campus Virtual Pregrados | L72: CVPR | M72: 35343 | N72: Programa - Departamento | O72: CVPR- Esc. Teología Filosofía y Hum-Med | P72: CVPR-ETFH | Q72: 6992 | R72: Course Template | S72: Centro de Humanidades-Med | T72: CVPR-MJHU | U72: ControlVersion
A73: 7373 | B73: Course Offering | C73: INTRODUCCIÓN A LAS ARTES PLÁSTICAS -MaestroC | D73: 2024-0010-MaestroC | E73: 6606 | F73: 1 | G73: Organization | H73: UPBVirtual | I73: 29006 | J73: Nivel | K73: Campus Virtual Pregrados | L73: CVPR | M73: 35343 | N73: Programa - Departamento | O73: CVPR- Esc. Teología Filosofía y Hum-Med | P73: CVPR-ETFH | Q73: 6992 | R73: Course Template | S73: Centro de Humanidades-Med | T73: CVPR-MJHU | U73: CMaestros
A74: 7374 | B74: Course Offering | C74: CFACH_Historia de la Cosmología_42619_201842 | D74: VREl_HistCosmologia_201842_42619 | E74: 6606 | F74: 1 | G74: Organization | H74: UPBVirtual | I74: 29010 | J74: Nivel | K74: Campus Virtual Posgrados | L74: CVFA | M74: 39281 | N74: Programa - Departamento | O74: CVFA-MF-Teología Filosofía y Hum-Med | P74: CVFA-MF | Q74: 6996 | R74: Course Template | S74: CVFA-MJHU-Centro de Humanidades-Med | T74: CVFA-MJHU | U74: 201842
... A132: 7712 | B132: Course Offering | C132: Bit Ness: Economía Basada en Redes_Clase Maestra | D132: BREl_BitNess_201820_60928-45404-51465 | E132: 6606 | F132: 1 | G132: Organization | H132: UPBVirtual | I132: 29013 | J132: Nivel | K132: Campus Virtual Extensión | L132: CVFC | M132: 35323 | N132: Programa - Departamento | O132: CVFC- Esc. Economía,Admon y Negocios-Med | P132: CVFC-ME | Q132: 8799 | R132: Course Template | S132: Plan_cursos_EscVerano Economia | T132: Plan_cursos_EscVerano_Eco | U132: 201820
A133: 7721 | B133: Course Offering | C133: Prototipo Html | D133: PROT_PrototipoHtml_2018_ | E133: 6606 | F133: 1 | G133: Organization | H133: UPBVirtual | I133: 29013 | J133: Nivel | K133: Campus Virtual Extensión | L133: CVFC | M133: 34493 | N133: Programa - Departamento | O133: CVFC- UPB Virtual | P133: CVFC-UPBV | Q133: 7208 | R133: Course Template | S133: Plan_ProgramaCursosEstudio | T133: Plan_ProgramaCursosEstudio
A134: 7722 | B134: Course Offering | C134: ECPD-Inducción a la educación virtual-MEN | D134: VROb_InduVirtualidad-FA_201820-MEN | E134: 6606 | F134: 1 | G134: Organization | H134: UPBVirtual | I134: 29010 | J134: Nivel | K134: Campus Virtual Posgrados | L134: CVFA | M134: 53969 | N134: Programa - Departamento | O134: CVFA-VI UPB Virtual | P134: CVFA-VI | Q134: 8211 | R134: Course Template | S134: CVFA-VPUV Plan_Inducción virtualidad | T134: CVFA-VPUV | U134: CMaestros
A135: 7722 | B135: Course Offering | C135: ECPD-Inducción a la educación virtual-MEN | D135: VROb_InduVirtualidad-FA_201820-MEN | E135: 6606 | F135: 1 | G135: Organization | H135: UPBVirtual | I135: 29010 | J135: Nivel | K135: Campus Virtual Posgrados | L135: CVFA | M135: 8210 | N135: Programa - Departamento | O135: CVFA- FormaciónUPBV - COL | P135: CVFA-UPBVIRTUAL | Q135: 8211 | R135: Course Template | S135: CVFA-VPUV Plan_Inducción virtualidad | T135: CVFA-VPUV | U135: CMaestros
A136: 7747 | B136: Course Offering | C136: Datos Vivos: Redes de lo vivo_Clase Maestra | D136: BREl_DatosVivos_201820_60924-45401-51459 | E136: 6606 | F136: 1 | G136: Organization | H136: UPBVirtual | I136: 29013 | J136: Nivel | K136: Campus Virtual Extensión | L136: CVFC | M136: 35289 | N136: Programa - Departamento | O136: CVFC- Escuela de Saberes | P136: CVFC-MXSB | Q136: 8802 | R136: Course Template | S136: Plan_cursos_EscVerano Ciencias Sociales | T136: Plan_cursos_EscVerano_Csoc | U136: 201820
A137: 7748 | B137: Course Offering | C137: ECPD_Inducción a la virtualidad | D137: VROb_IntroVirtualidad_201842_45419 | E137: 6606 | F137: 1 | G137: Organization | H137: UPBVirtual | I137: 29010 | J137: Nivel | K137: Campus Virtual Posgrados | L137: CVFA | M137: 53969 | N137: Programa - Departamento | O137: CVFA-VI UPB Virtual | P137: CVFA-VI | Q137: 8211 | R137: Course Template | S137: CVFA-VPUV Plan_Inducción virtualidad | T137: CVFA-VPUV | U137: 201842
A138: 7748 | B138: Course Offering | C138: ECPD_Inducción a la virtualidad | D138: VROb_IntroVirtualidad_201842_45419 | E138: 6606 | F138: 1 | G138: Organization | H138: UPBVirtual | I138: 29010 | J138: Nivel | K138: Campus Virtual Posgrados | L138: CVFA | M138: 8210 | N138: Programa - Departamento | O138: CVFA- FormaciónUPBV - COL | P138: CVFA-UPBVIRTUAL | Q138: 8211 | R138: Course Template | S138: CVFA-VPUV Plan_Inducción virtualidad | T138: CVFA-VPUV | U138: 201842
A139: 7749 | B139: Course Offering | C139: EGP_Gestión Estratégica-201842_45197 | D139: WSOb_EGPGesEstra_201842_45197 | E139: 6606 | F139: 1 | G139: Organization | H139: UPBVirtual | I139: 29010 | J139: Nivel | K139: Campus Virtual Posgrados | L139: CVFA | M139: 35352 | N139: Programa - Departamento | O139: CVFA-BI-Ingeniería-Bga | P139: CVFA-BI | Q139: 6691 | R139: Course Template | S139: CVFA-VEGP- Esp. Gestión de Proyectos-Virt | T139: CVFA-VEGP | U139: 201842
A140: 7759 | B140: Course Offering | C140: DE_Ética e historia de la investigación_Maestro | D140: ADEl_DEEticHistInves_201842_NRC | E140: 6606 | F140: 1 | G140: Organization | H140: UPBVirtual | I140: 34416 | J140: Nivel | K140: Campus B-Learning 2.0 Posgrados | L140: CBFA | M140: 35311 | N140: Programa - Departamento | O140: CBFA-Esc. Educación y Pedagogía-Med | P140: CBFA-MP | Q140: 7758 | R140: Course Template | S140: Plan_DoctoradoEducacion | T140: Plan_DoctoradoEducacion | U140: CMaestros
A141: 7760 | B141: Course Offering | C141: DE_Formación Investigativa I-201842 | D141: ADOb_DeFormInvesI_201842_NRC | E141: 6606 | F141: 1 | G141: Organization | H141: UPBVirtual | I141: 34416 | J141: Nivel | K141: Campus B-Learning 2.0 Posgrados | L141: CBFA | M141: 35311 | N141: Programa - Departamento | O141: CBFA-Esc. Educación y Pedagogía-Med | P141: CBFA-MP | Q141: 7758 | R141: Course Template | S141: Plan_DoctoradoEducacion | T141: Plan_DoctoradoEducacion
A142: 7761 | B142: Course Offering | C142: DE_Problematizaciones I. Pensamiento y pensadores de la educación (Introducción a la teoría crítica)-MaestroC | D142: 3313-0024-MaestroC | E142: 6606 | F142: 1 | G142: Organization | H142: UPBVirtual | I142: 34416 | J142: Nivel | K142: Campus B-Learning 2.0 Posgrados | L142: CBFA | M142: 35311 | N142: Programa - Departamento | O142: CBFA-Esc. Educación y Pedagogía-Med | P142: CBFA-MP | Q142: 7758 | R142: Course Template | S142: Plan_DoctoradoEducacion | T142: Plan_DoctoradoEducacion | U142: CMaestros
A143: 7768 | B143: Course Offering | C143: Civilización islámica: cultura sociedad y política -MaestroC | D143: 5556-0099-MaestroC | E143: 6606 | F143: 1 | G143: Organization | H143: UPBVirtual | I143: 29006 | J143: Nivel | K143: Campus Virtual Pregrados | L143: CVPR | M143: 35337 | N143: Programa - Departamento | O143: CVPR- Esc. Derecho Ciencias Políticas-Med | P143: CVPR-MD | Q143: 8750 | R143: Course Template | S143: PR Ciencias Políticas - Med | T143: MCPO | U143: CMaestros
A144: 7771 | B144: Course Offering | C144: (Viejo)Reto al Saber_-MaestroV | D144: VREl_ViejoRetoSaber_201820_-MaestroV | E144: 6606 | F144: 1 | G144: Organization | H144: UPBVirtual | I144: 29013 | J144: Nivel | K144: Campus Virtual Extensión | L144: CVFC | M144: 35330 | N144: Programa - Departamento | O144: CVFC- Vicerrectoría Académica - Med | P144: CVFC-VACAD | Q144: 7770 | R144: Course Template | S144: Plan_CursoFormaDDMed | T144: Plan_CursoFormaDDMed | U144: ControlVersion
A145: 7774 | B145: Course Offering | C145: (MEN)MPSI_Inclusión escolar_Maestro-MEN | D145: BROb_MPSIIncluEscolar-MEN_201820_CMaestro | E145: 6606 | F145: 1 | G145: Organization | H145: UPBVirtual | I145: 29010 | J145: Nivel | K145: Campus Virtual Posgrados | L145: CVFA | M145: 35351 | N145: Programa - Departamento | O145: CVFA-VSEP-Educación y Pedagogía-Med | P145: CVFA-VSEP | Q145: 7116 | R145: Course Template | S145: CVFA-VMEP- Mtría en Psicopedagogía-Vir | T145: CVFA-VMEP | U145: MEN
A146: 7775 | B146: Course Offering | C146: MPSI_Fundamentación Psicopedagógica (Bimodal)_Maestro | D146: Funda-PsicoBimo-Maestro | E146: 6606 | F146: 1 | G146: Organization | H146: UPBVirtual | I146: 29010 | J146: Nivel | K146: Campus Virtual Posgrados | L146: CVFA | M146: 35351 | N146: Programa - Departamento | O146: CVFA-VSEP-Educación y Pedagogía-Med | P146: CVFA-VSEP | Q146: 7116 | R146: Course Template | S146: CVFA-VMEP- Mtría en Psicopedagogía-Vir | T146: CVFA-VMEP | U146: CMaestros
A147: 7776 | B147: Course Offering | C147: MPSI_Técnicas de Evaluación e Intervención Psicopedagógica (Bimodal) - HTMaestroC | D147: PSED-0024-MaestroC | E147: 6606 | F147: 1 | G147: Organization | H147: UPBVirtual | I147: 29010 | J147: Nivel | K147: Campus Virtual Posgrados | L147: CVFA | M147: 35351 | N147: Programa - Departamento | O147: CVFA-VSEP-Educación y Pedagogía-Med | P147: CVFA-VSEP | Q147: 7116 | R147: Course Template | S147: CVFA-VMEP- Mtría en Psicopedagogía-Vir | T147: CVFA-VMEP | U147: CMaestros
A148: 7779 | B148: Course Offering | C148: (MEN)MSL_The limit experience -MEN | D148: WDMa_MSLTheLimitExpeMEN_201842_-MEN | E148: 6606 | F148: 1 | G148: Organization | H148: UPBVirtual | I148: 29010 | J148: Nivel | K148: Campus Virtual Posgrados | L148: CVFA | M148: 35351 | N148: Programa - Departamento | O148: CVFA-VSEP-Educación y Pedagogía-Med | P148: CVFA-VSEP | Q148: 7778 | R148: Course Template | S148: CVFA-VMPA-Mtría Proce Aprend Seg Len-Vir | T148: CVFA-VMPA | U148: MEN
A149: 7781 | B149: Course Offering | C149: (MEN)MSL_Introduction to Academic Discourse -MEN | D149: WDMa_MSLIntroAcadDisc_201842_-MEN | E149: 6606 | F149: 1 | G149: Organization | H149: UPBVirtual | I149: 29010 | J149: Nivel | K149: Campus Virtual Posgrados | L149: CVFA | M149: 35351 | N149: Programa - Departamento | O149: CVFA-VSEP-Educación y Pedagogía-Med | P149: CVFA-VSEP | Q149: 7778 | R149: Course Template | S149: CVFA-VMPA-Mtría Proce Aprend Seg Len-Vir | T149: CVFA-VMPA | U149: MEN
A150: 7784 | B150: Course Offering | C150: (MEN)ME_Contexto Socioeducativo_-MEN | D150: WROb_MEContSocio_201842MEN__-MEN | E150: 6606 | F150: 1 | G150: Organization | H150: UPBVirtual | I150: 29010 | J150: Nivel | K150: Campus Virtual Posgrados | L150: CVFA | M150: 35351 | N150: Programa - Departamento | O150: CVFA-VSEP-Educación y Pedagogía-Med | P150: CVFA-VSEP | Q150: 7783 | R150: Course Template | S150: CVFA-VMEE- Mtría en Educación-Virtual | T150: CVFA-VMEE | U150: MEN
A151: 7785 | B151: Course Offering | C151: (MEN)ME_Investigación Educativa I_-MEN | D151: WDEl_MEInvesEducaI_201820_-MEN | E151: 6606 | F151: 1 | G151: Organization | H151: UPBVirtual | I151: 29010 | J151: Nivel | K151: Campus Virtual Posgrados | L151: CVFA | M151: 35351 | N151: Programa - Departamento | O151: CVFA-VSEP-Educación y Pedagogía-Med | P151: CVFA-VSEP | Q151: 7783 | R151: Course Template | S151: CVFA-VMEE- Mtría en Educación-Virtual | T151: CVFA-VMEE | U151: MEN
A152: 7786 | B152: Course Offering | C152: TECNOLOGÍA-COMUNICACIÓN-EDUCACIÓN -MaestroV | D152: PGME-0033-MaestroV | E152: 6606 | F152: 1 | G152: Organization | H152: UPBVirtual | I152: 29010 | J152: Nivel | K152: Campus Virtual Posgrados | L152: CVFA | M152: 35351 | N152: Programa - Departamento | O152: CVFA-VSEP-Educación y Pedagogía-Med | P152: CVFA-VSEP | Q152: 7783 | R152: Course Template | S152: CVFA-VMEE- Mtría en Educación-Virtual | T152: CVFA-VMEE | U152: ControlVersion
A153: 7787 | B153: Course Offering | C153: Ruta para el diseño ambientes virtuales de aprendizaje 201820 Maestro | D153: Ambientes-Virtuales-CMaestro | E153: 6606 | F153: 1 | G153: Organization | H153: UPBVirtual | I153: 29013 | J153: Nivel | K153: Campus Virtual Extensión | L153: CVFC | M153: 34493 | N153: Programa - Departamento | O153: CVFC- UPB Virtual | P153: CVFC-UPBV | Q153: 7138 | R153: Course Template | S153: Plan_cursos_FormUPBV | T153: FormUPBV | U153: CMaestros
... A189: 7959 | B189: Course Offering | C189: Ética en la red | D189: VREl_EticaRed_201842_46043 | E189: 6606 | F189: 1 | G189: Organization | H189: UPBVirtual | I189: 29010 | J189: Nivel | K189: Campus Virtual Posgrados | L189: CVFA | M189: 39281 | N189: Programa - Departamento | O189: CVFA-MF-Teología Filosofía y Hum-Med | P189: CVFA-MF | Q189: 6996 | R189: Course Template | S189: CVFA-MJHU-Centro de Humanidades-Med | T189: CVFA-MJHU | U189: 201842
A190: 7975 | B190: Course Offering | C190: Curso Taller ePortafolio | D190: TEMP_CursoTallerEporta_2018_ | E190: 6606 | F190: 1 | G190: Organization | H190: UPBVirtual | I190: 29013 | J190: Nivel | K190: Campus Virtual Extensión | L190: CVFC | M190: 34493 | N190: Programa - Departamento | O190: CVFC- UPB Virtual | P190: CVFC-UPBV | Q190: 7208 | R190: Course Template | S190: Plan_ProgramaCursosEstudio | T190: Plan_ProgramaCursosEstudio
A191: 7978 | B191: Course Offering | C191: DE_Realidades y tendencias del contexto socio-educativo-201842 | D191: ADOb_DEContSociEdu_201842_NRC | E191: 6606 | F191: 1 | G191: Organization | H191: UPBVirtual | I191: 34416 | J191: Nivel | K191: Campus B-Learning 2.0 Posgrados | L191: CBFA | M191: 35311 | N191: Programa - Departamento | O191: CBFA-Esc. Educación y Pedagogía-Med | P191: CBFA-MP | Q191: 7758 | R191: Course Template | S191: Plan_DoctoradoEducacion | T191: Plan_DoctoradoEducacion | U191: 201842
A192: 7987 | B192: Course Offering | C192: GEICO Coordinación de la maestría | D192: PDOb_GEICOCoorMaestria_2023_ | E192: 6606 | F192: 1 | G192: Organization | H192: UPBVirtual | I192: 29010 | J192: Nivel | K192: Campus Virtual Posgrados | L192: CVFA | M192: 35350 | N192: Programa - Departamento | O192: CVFA-ME-Economía,Admon y Negocios-Med | P192: CVFA-ME | Q192: 7986 | R192: Course Template | S192: CVFA-VMGE- Mtría Gtion Estra Inf Con-Virt | T192: CVFA-VMGE | U192: CoordProgramas
A193: 7989 | B193: Course Offering | C193: Ética de las Organizaciones | D193: VREl_CFACHEticOrga_201842_46196 | E193: 6606 | F193: 1 | G193: Organization | H193: UPBVirtual | I193: 29010 | J193: Nivel | K193: Campus Virtual Posgrados | L193: CVFA | M193: 39281 | N193: Programa - Departamento | O193: CVFA-MF-Teología Filosofía y Hum-Med | P193: CVFA-MF | Q193: 6996 | R193: Course Template | S193: CVFA-MJHU-Centro de Humanidades-Med | T193: CVFA-MJHU | U193: 201842
...

Sheet CursosBS
A1: ﻿OrgUnitId | B1: Organization | C1: Type | D1: Name | E1: Code | F1: StartDate | G1: EndDate | H1: IsActive | I1: CreatedDate | J1: IsDeleted | K1: DeletedDate | L1: RecycledDate | M1: Version | N1: OrgUnitTypeId | O1: PERIODO-NRC
A2: 80246 | B2: UPBVirtual | C2: Course Offering | D2: Transición en los mercados de energía - 202641-51368 | E2: 8828-2013-202641-51368 | H2: TRUE | I2: 46071.016 | J2: FALSE | M2: 442114873346 | N2: 3 | O2: =(RIGHT(CursosBS_2[[#This Row],[Code]],12)) -> 202641-51368
A3: 80245 | B3: UPBVirtual | C3: Course Offering | D3: SEMINARIO DE INVESTIGACIÓN II - 202641-51135 | E3: 3313-2053-202641-51135 | H3: TRUE | I3: 46071.016 | J3: FALSE | M3: 442114872903 | N3: 3 | O3: =(RIGHT(CursosBS_2[[#This Row],[Code]],12)) -> 202641-51135
A4: 80244 | B4: UPBVirtual | C4: Course Offering | D4: DISEÑO DE EXPERIMENTOS - 202641-51129 | E4: 9937-2002-202641-51129 | H4: TRUE | I4: 46071.015 | J4: FALSE | M4: 442114872452 | N4: 3 | O4: =(RIGHT(CursosBS_2[[#This Row],[Code]],12)) -> 202641-51129
A5: 80243 | B5: UPBVirtual | C5: Course Offering | D5: SEGURIDAD INFORMÁTICA Y EVALUACIÓN DE RIESGOS DE TI - 202641-51428 | E5: 8827-2009-202641-51428 | H5: TRUE | I5: 46071.014 | J5: FALSE | M5: 442114872084 | N5: 3 | O5: =(RIGHT(CursosBS_2[[#This Row],[Code]],12)) -> 202641-51428
A6: 80236 | B6: UPBVirtual | C6: Course Offering | D6: GERENCIA CONTEMPORÁNEA - 202641-52251 | E6: 6069-2060-202641-52251 | H6: TRUE | I6: 46071.013 | J6: FALSE | M6: 442114871685 | N6: 3 | O6: =(RIGHT(CursosBS_2[[#This Row],[Code]],12)) -> 202641-52251
A7: 80228 | B7: UPBVirtual | C7: Course Offering | D7: ENTORNO ECONÓMICO - 202641-52199 | E7: 6611-2020V-202641-52199 | H7: TRUE | I7: 46071.012 | J7: FALSE | M7: 442114871164 | N7: 3 | O7: =(RIGHT(CursosBS_2[[#This Row],[Code]],12)) -> 202641-52199
A8: 80227 | B8: UPBVirtual | C8: Course Offering | D8: Empresa e impuestos - 202641-51671 | E8: 5559-2057V-202641-51671 | H8: TRUE | I8: 46071.011 | J8: FALSE | M8: 442114870600 | N8: 3 | O8: =(RIGHT(CursosBS_2[[#This Row],[Code]],12)) -> 202641-51671
A9: 80216 | B9: UPBVirtual | C9: Course Offering | D9: Oralidad procesal - 202641-51686 | E9: 5559-2090V-202641-51686 | H9: TRUE | I9: 46071.01 | J9: FALSE | M9: 442114870205 | N9: 3 | O9: =(RIGHT(CursosBS_2[[#This Row],[Code]],12)) -> 202641-51686
A10: 80215 | B10: UPBVirtual | C10: Course Offering | D10: LENGUAJE VISUAL - QMMaestroP(T) | E10: 2027-5009V-MaestroP | H10: TRUE | I10: 46070.819 | J10: FALSE | M10: 442114842881 | N10: 3 | O10: =(RIGHT(CursosBS_2[[#This Row],[Code]],12)) -> 09V-MaestroP
A11: 80214 | B11: UPBVirtual | C11: Course Offering | D11: Seminario de Formación Investigativa II - QMMaestroP(T) | E11: 3313-2129-MaestroP | H11: TRUE | I11: 46070.816 | J11: FALSE | M11: 442114841973 | N11: 3 | O11: =(RIGHT(CursosBS_2[[#This Row],[Code]],12)) -> 129-MaestroP
A12: 80203 | B12: UPBVirtual | C12: Course Offering | D12: Economía para los negocios - 202641-52212 | E12: 6611-2035V-202641-52212 | H12: TRUE | I12: 46070.654 | J12: FALSE | M12: 442114826079 | N12: 3 | O12: =(RIGHT(CursosBS_2[[#This Row],[Code]],12)) -> 202641-52212
A13: 80168 | B13: UPBVirtual | C13: Course Offering | D13: Bienestar e incentivos - 202641-52001 | E13: 5566-2048V-202641-52001 | H13: TRUE | I13: 46070.535 | J13: FALSE | M13: 442114814059 | N13: 3 | O13: =(RIGHT(CursosBS_2[[#This Row],[Code]],12)) -> 202641-52001
... A34: 80003 | B34: UPBVirtual | C34: Course Offering | D34: Ética, Ciencia y Cultura - 202641-58288 | E34: 5568-0079-202641-58288 | H34: TRUE | I34: 46066.799 | J34: FALSE | M34: 442114480561 | N34: 3 | O34: =(RIGHT(CursosBS_2[[#This Row],[Code]],12)) -> 202641-58288
A35: 80002 | B35: UPBVirtual | C35: Course Offering | D35: Técnicas y Herramientas prospectivas 1 | E35: 6069-2002-202641V2-57808 | F35: 46083 | G35: 46107.999 | H35: TRUE | I35: 46066.737 | J35: FALSE | M35: 442114475961 | N35: 3 | O35: =(RIGHT(CursosBS_2[[#This Row],[Code]],12)) -> 2641V2-57808
A36: 80001 | B36: UPBVirtual | C36: Course Offering | D36: Indicadores de gestión | E36: 6069-2008V-202641V2-57809 | F36: 46083 | G36: 46107.999 | H36: TRUE | I36: 46066.736 | J36: FALSE | M36: 442114475934 | N36: 3 | O36: =(RIGHT(CursosBS_2[[#This Row],[Code]],12)) -> 2641V2-57809
A37: 80000 | B37: UPBVirtual | C37: Course Offering | D37: Técnicas y Herramientas prospectivas 2 | E37: 6069-2003-202641V2-50030 | F37: 46083 | G37: 46107.999 | H37: TRUE | I37: 46066.734 | J37: FALSE | M37: 442114475889 | N37: 3 | O37: =(RIGHT(CursosBS_2[[#This Row],[Code]],12)) -> 2641V2-50030
A38: 79999 | B38: UPBVirtual | C38: Course Offering | D38: Seminario de investigación II | E38: 6069-2154-202641V2-57807 | F38: 46083 | G38: 46107.999 | H38: TRUE | I38: 46066.733 | J38: FALSE | M38: 442114475845 | N38: 3 | O38: =(RIGHT(CursosBS_2[[#This Row],[Code]],12)) -> 2641V2-57807
A39: 79998 | B39: UPBVirtual | C39: Course Offering | D39: Mega tendencias y Escenarios Mundiales | E39: 6069-0174-202641V2-50033 | F39: 46083 | G39: 46107.999 | H39: TRUE | I39: 46066.732 | J39: FALSE | M39: 442114475779 | N39: 3 | O39: =(RIGHT(CursosBS_2[[#This Row],[Code]],12)) -> 2641V2-50033
A40: 79997 | B40: UPBVirtual | C40: Course Offering | D40: Prospectiva estratégica | E40: 6069-0154-202641V2-50032 | F40: 46083 | G40: 46107.999 | H40: TRUE | I40: 46066.732 | J40: FALSE | M40: 442114475712 | N40: 3 | O40: =(RIGHT(CursosBS_2[[#This Row],[Code]],12)) -> 2641V2-50032
A41: 79996 | B41: UPBVirtual | C41: Course Offering | D41: Fundamentación psicopedagógica | E41: 3313-0046-202641V2-58603 | F41: 46083 | G41: 46107.999 | H41: TRUE | I41: 46066.728 | J41: FALSE | M41: 442114475492 | N41: 3 | O41: =(RIGHT(CursosBS_2[[#This Row],[Code]],12)) -> 2641V2-58603
A42: 79995 | B42: UPBVirtual | C42: Course Offering | D42: Fundamentación pedagógica | E42: 3313-0047-202641V2-58604 | F42: 46083 | G42: 46107.999 | H42: TRUE | I42: 46066.727 | J42: FALSE | M42: 442114475433 | N42: 3 | O42: =(RIGHT(CursosBS_2[[#This Row],[Code]],12)) -> 2641V2-58604
A43: 79994 | B43: UPBVirtual | C43: Course Offering | D43: Seminario de investigación I | E43: 3313-0051-202641V2-58605 | F43: 46083 | G43: 46107.999 | H43: TRUE | I43: 46066.726 | J43: FALSE | M43: 442114475363 | N43: 3 | O43: =(RIGHT(CursosBS_2[[#This Row],[Code]],12)) -> 2641V2-58605
A44: 79993 | B44: UPBVirtual | C44: Course Offering | D44: Educación inclusiva y psicopedagogía | E44: 3313-0050-202641V2-57843 | F44: 46083 | G44: 46107.999 | H44: TRUE | I44: 46066.725 | J44: FALSE | M44: 442114475322 | N44: 3 | O44: =(RIGHT(CursosBS_2[[#This Row],[Code]],12)) -> 2641V2-57843
A45: 79992 | B45: UPBVirtual | C45: Course Offering | D45: Ética, ciencia y cultura | E45: 5568-0079-202641V2-57844 | F45: 46083 | G45: 46107.999 | H45: TRUE | I45: 46066.724 | J45: FALSE | M45: 442114475275 | N45: 3 | O45: =(RIGHT(CursosBS_2[[#This Row],[Code]],12)) -> 2641V2-57844
A46: 79991 | B46: UPBVirtual | C46: Course Offering | D46: Psicopedagogía y contextos sociales | E46: 3313-0048-202641V2-57816 | F46: 46083 | G46: 46107.999 | H46: TRUE | I46: 46066.724 | J46: FALSE | M46: 442114475228 | N46: 3 | O46: =(RIGHT(CursosBS_2[[#This Row],[Code]],12)) -> 2641V2-57816
... A54: 79983 | B54: UPBVirtual | C54: Course Offering | D54: Ejercicio De Investigación I | E54: 3313-2010-202641V2-58075 | F54: 46083 | G54: 46107.999 | H54: TRUE | I54: 46066.714 | J54: FALSE | M54: 442114474498 | N54: 3 | O54: =(RIGHT(CursosBS_2[[#This Row],[Code]],12)) -> 2641V2-58075
A55: 79982 | B55: UPBVirtual | C55: Course Offering | D55: Teoría y crítica del proyecto de diseño - 202641-51744 | E55: 2027-2023V-202641-51744 | H55: TRUE | I55: 46066.713 | J55: FALSE | M55: 442114474517 | N55: 3 | O55: =(RIGHT(CursosBS_2[[#This Row],[Code]],12)) -> 202641-51744
A56: 79981 | B56: UPBVirtual | C56: Course Offering | D56: Seminario de Investigación I: Articulo-Estudio de caso | E56: 6069-2153-202641V2-58607 | F56: 46083 | G56: 46107.999 | H56: TRUE | I56: 46066.713 | J56: FALSE | M56: 442114474193 | N56: 3 | O56: =(RIGHT(CursosBS_2[[#This Row],[Code]],12)) -> 2641V2-58607
A57: 79980 | B57: UPBVirtual | C57: Course Offering | D57: Planeación y Formulación de Proyectos | E57: 6069-2156-202641V2-58606 | F57: 46083 | G57: 46107.999 | H57: TRUE | I57: 46066.71 | J57: FALSE | M57: 442114473986 | N57: 3 | O57: =(RIGHT(CursosBS_2[[#This Row],[Code]],12)) -> 2641V2-58606
A58: 79979 | B58: UPBVirtual | C58: Course Offering | D58: Gestión del Cronograma, Costos y Riesgos | E58: 6069-2157-202641V2-58925 | F58: 46083 | G58: 46107.999 | H58: TRUE | I58: 46066.71 | J58: FALSE | M58: 442114473918 | N58: 3 | O58: =(RIGHT(CursosBS_2[[#This Row],[Code]],12)) -> 2641V2-58925
A59: 79978 | B59: UPBVirtual | C59: Course Offering | D59: Gestión del Cronograma, Costos y Riesgos | E59: 6069-2157-202641V2-57804 | F59: 46083 | G59: 46107.999 | H59: TRUE | I59: 46066.709 | J59: FALSE | M59: 442114473808 | N59: 3 | O59: =(RIGHT(CursosBS_2[[#This Row],[Code]],12)) -> 2641V2-57804
A60: 79977 | B60: UPBVirtual | C60: Course Offering | D60: Seminario de Investigación II: Articulo-Estudio de cas | E60: 6069-2154-202641V2-57803 | F60: 46083 | G60: 46107.999 | H60: TRUE | I60: 46066.708 | J60: FALSE | M60: 442114473744 | N60: 3 | O60: =(RIGHT(CursosBS_2[[#This Row],[Code]],12)) -> 2641V2-57803
A61: 79976 | B61: UPBVirtual | C61: Course Offering | D61: Evaluación y Gestión Financiera de Proyectos | E61: 6611-0036-202641V2-57888 | F61: 46083 | G61: 46107.999 | H61: TRUE | I61: 46066.707 | J61: FALSE | M61: 442114473640 | N61: 3 | O61: =(RIGHT(CursosBS_2[[#This Row],[Code]],12)) -> 2641V2-57888
A62: 79975 | B62: UPBVirtual | C62: Course Offering | D62: Estudios de Viabilidad de Proyectos | E62: 6611-0035-202641V2-57873 | F62: 46083 | G62: 46107.999 | H62: TRUE | I62: 46066.706 | J62: FALSE | M62: 442114473575 | N62: 3 | O62: =(RIGHT(CursosBS_2[[#This Row],[Code]],12)) -> 2641V2-57873
A63: 79974 | B63: UPBVirtual | C63: Course Offering | D63: Gestión Estratégica | E63: 6069-2158-202641V2-57877 | F63: 46083 | G63: 46107.999 | H63: TRUE | I63: 46066.676 | J63: FALSE | M63: 442114470973 | N63: 3 | O63: =(RIGHT(CursosBS_2[[#This Row],[Code]],12)) -> 2641V2-57877
A64: 79973 | B64: UPBVirtual | C64: Course Offering | D64: Seminario de Investigación II: Articulo-Estudio de cas | E64: 6069-2154-202641V2-57878 | F64: 46083 | G64: 46107.999 | H64: TRUE | I64: 46066.674 | J64: FALSE | M64: 442114470776 | N64: 3 | O64: =(RIGHT(CursosBS_2[[#This Row],[Code]],12)) -> 2641V2-57878
A65: 79972 | B65: UPBVirtual | C65: Course Offering | D65: Gestión Ágil de Proyectos | E65: 6069-2160-202641V2-57875 | F65: 46083 | G65: 46107.999 | H65: TRUE | I65: 46066.673 | J65: FALSE | M65: 442114470596 | N65: 3 | O65: =(RIGHT(CursosBS_2[[#This Row],[Code]],12)) -> 2641V2-57875
A66: 79971 | B66: UPBVirtual | C66: Course Offering | D66: Gestión de la Calidad y Adquisiciones | E66: 6069-2159-202641V2-57876 | F66: 46083 | G66: 46107.999 | H66: TRUE | I66: 46066.665 | J66: FALSE | M66: 442114469858 | N66: 3 | O66: =(RIGHT(CursosBS_2[[#This Row],[Code]],12)) -> 2641V2-57876
A67: 79970 | B67: UPBVirtual | C67: Course Offering | D67: Electiva: Ética de las organizaciones | E67: 5568-0073-202641V2-58924 | F67: 46083 | G67: 46107.999 | H67: TRUE | I67: 46066.663 | J67: FALSE | M67: 442114469536 | N67: 3 | O67: =(RIGHT(CursosBS_2[[#This Row],[Code]],12)) -> 2641V2-58924
A68: 79969 | B68: UPBVirtual | C68: Course Offering | D68: Electiva: Ética de las organizaciones | E68: 5568-0073-202641V2-AP8 | F68: 46083 | G68: 46107.999 | H68: TRUE | I68: 46066.649 | J68: FALSE | M68: 442114468188 | N68: 3 | O68: =(RIGHT(CursosBS_2[[#This Row],[Code]],12)) -> 202641V2-AP8
A69: 79968 | B69: UPBVirtual | C69: Course Offering | D69: READING COMPREHENSION STRATEGIES - 202650-51299 | E69: IDIO-0014-202650-51299 | H69: TRUE | I69: 46066.647 | J69: FALSE | M69: 442114468113 | N69: 3 | O69: =(RIGHT(CursosBS_2[[#This Row],[Code]],12)) -> 202650-51299
A70: 79967 | B70: UPBVirtual | C70: Course Offering | D70: Evaluación y Gestión del Riesgo | E70: 6611-0038-202641V2-50023 | F70: 46083 | G70: 46107.999 | H70: TRUE | I70: 46066.646 | J70: FALSE | M70: 442114467749 | N70: 3 | O70: =(RIGHT(CursosBS_2[[#This Row],[Code]],12)) -> 2641V2-50023
A71: 79966 | B71: UPBVirtual | C71: Course Offering | D71: Estándares Internacionales de Proyectos | E71: 6069-2161-202641V2-58923 | F71: 46083 | G71: 46107.999 | H71: TRUE | I71: 46066.645 | J71: FALSE | M71: 442114467615 | N71: 3 | O71: =(RIGHT(CursosBS_2[[#This Row],[Code]],12)) -> 2641V2-58923
A72: 79965 | B72: UPBVirtual | C72: Course Offering | D72: Estándares Internacionales de Proyectos | E72: 6069-2161-202641V2-57872 | F72: 46083 | G72: 46107.999 | H72: TRUE | I72: 46066.642 | J72: FALSE | M72: 442114467299 | N72: 3 | O72: =(RIGHT(CursosBS_2[[#This Row],[Code]],12)) -> 2641V2-57872
A73: 79964 | B73: UPBVirtual | C73: Course Offering | D73: Aspectos Legales y Contratación en los Proyectos | E73: 5559-0110-202641V2-AP10 | F73: 46083 | G73: 46107.999 | H73: TRUE | I73: 46066.641 | J73: FALSE | M73: 442114467195 | N73: 3 | O73: =(RIGHT(CursosBS_2[[#This Row],[Code]],12)) -> 02641V2-AP10
A74: 79963 | B74: UPBVirtual | C74: Course Offering | D74: Aspectos Legales y Contratación en los Proyectos | E74: 5559-0110-202641V2-50019 | F74: 46083 | G74: 46107.999 | H74: TRUE | I74: 46066.64 | J74: FALSE | M74: 442114467076 | N74: 3 | O74: =(RIGHT(CursosBS_2[[#This Row],[Code]],12)) -> 2641V2-50019
A75: 79962 | B75: UPBVirtual | C75: Course Offering | D75: OPTATIVA: Gerencia y organización empresarial | E75: 6069-2156V-202641V2-AP12 | F75: 46083 | G75: 46107.999 | H75: TRUE | I75: 46066.638 | J75: FALSE | M75: 442114466827 | N75: 3 | O75: =(RIGHT(CursosBS_2[[#This Row],[Code]],12)) -> 02641V2-AP12
A76: 79961 | B76: UPBVirtual | C76: Course Offering | D76: Electiva: Ética en la red | E76: 5568-0074-202641V2-AP11 | F76: 46083 | G76: 46107.999 | H76: TRUE | I76: 46066.635 | J76: FALSE | M76: 442114466501 | N76: 3 | O76: =(RIGHT(CursosBS_2[[#This Row],[Code]],12)) -> 02641V2-AP11
A77: 79915 | B77: UPBVirtual | C77: Course Offering | D77: Electiva: Ética en la red | E77: 5568-0074-202641V2-58057 | F77: 46083 | G77: 46107.999 | H77: TRUE | I77: 46065.952 | J77: FALSE | M77: 442114418049 | N77: 3 | O77: =(RIGHT(CursosBS_2[[#This Row],[Code]],12)) -> 2641V2-58057
A78: 79908 | B78: UPBVirtual | C78: Course Offering | D78: ABC Brightspace Taller 2026-1 - Yurany Andrea Herrera Cardenas | E78: ABC_BRTALL2026-1-000405990 | H78: TRUE | I78: 46065.622 | J78: FALSE | M78: 442114383308 | N78: 3 | O78: =(RIGHT(CursosBS_2[[#This Row],[Code]],12)) -> -1-000405990
A79: 79906 | B79: UPBVirtual | C79: Course Offering | D79: ABC Brightspace Taller 2026-1 - Juan Sebastian Cardenas Restrepo | E79: ABC_BRTALL2026-1-000613543 | H79: TRUE | I79: 46065.621 | J79: FALSE | M79: 442114382841 | N79: 3 | O79: =(RIGHT(CursosBS_2[[#This Row],[Code]],12)) -> -1-000613543
A80: 79904 | B80: UPBVirtual | C80: Course Offering | D80: ABC Brightspace Taller 2026-1 - Analia Cecilia Cervini | E80: ABC_BRTALL2026-1-000126837 | H80: TRUE | I80: 46065.619 | J80: FALSE | M80: 442114382323 | N80: 3 | O80: =(RIGHT(CursosBS_2[[#This Row],[Code]],12)) -> -1-000126837
A81: 79902 | B81: UPBVirtual | C81: Course Offering | D81: ABC Brightspace Taller 2026-1 - Maria Isabel Velez Lopez | E81: ABC_BRTALL2026-1-000613532 | H81: TRUE | I81: 46065.618 | J81: FALSE | M81: 442114381837 | N81: 3 | O81: =(RIGHT(CursosBS_2[[#This Row],[Code]],12)) -> -1-000613532
A82: 79900 | B82: UPBVirtual | C82: Course Offering | D82: ABC Brightspace Taller 2026-1 - Angy Paola Zambrano Rodriguez | E82: ABC_BRTALL2026-1-000335774 | H82: TRUE | I82: 46065.617 | J82: FALSE | M82: 442114381312 | N82: 3 | O82: =(RIGHT(CursosBS_2[[#This Row],[Code]],12)) -> -1-000335774
A83: 79898 | B83: UPBVirtual | C83: Course Offering | D83: ABC Brightspace Taller 2026-1 - Daniela Cano Calle | E83: ABC_BRTALL2026-1-000493273 | H83: TRUE | I83: 46065.616 | J83: FALSE | M83: 442114380824 | N83: 3 | O83: =(RIGHT(CursosBS_2[[#This Row],[Code]],12)) -> -1-000493273
A84: 79894 | B84: UPBVirtual | C84: Course Offering | D84: ABC Brightspace Taller 2026-1 -OPC15 | E84: ABC_BRTALL2026-1-OPC15 | H84: TRUE | I84: 46065.061 | J84: FALSE | M84: 442114353368 | N84: 3 | O84: =(RIGHT(CursosBS_2[[#This Row],[Code]],12)) -> 2026-1-OPC15
A85: 79892 | B85: UPBVirtual | C85: Course Offering | D85: ABC Brightspace Taller 2026-1 -OPC14 | E85: ABC_BRTALL2026-1-OPC14 | H85: TRUE | I85: 46065.06 | J85: FALSE | M85: 442114352846 | N85: 3 | O85: =(RIGHT(CursosBS_2[[#This Row],[Code]],12)) -> 2026-1-OPC14
A86: 79890 | B86: UPBVirtual | C86: Course Offering | D86: ABC Brightspace Taller 2026-1 -OPC13 | E86: ABC_BRTALL2026-1-OPC13 | H86: TRUE | I86: 46065.059 | J86: FALSE | M86: 442114352363 | N86: 3 | O86: =(RIGHT(CursosBS_2[[#This Row],[Code]],12)) -> 2026-1-OPC13
A87: 79888 | B87: UPBVirtual | C87: Course Offering | D87: ABC Brightspace Taller 2026-1 -OPC12 | E87: ABC_BRTALL2026-1-OPC12 | H87: TRUE | I87: 46065.059 | J87: FALSE | M87: 442114351819 | N87: 3 | O87: =(RIGHT(CursosBS_2[[#This Row],[Code]],12)) -> 2026-1-OPC12
A88: 79886 | B88: UPBVirtual | C88: Course Offering | D88: ABC Brightspace Taller 2026-1 -OPC11 | E88: ABC_BRTALL2026-1-OPC11 | H88: TRUE | I88: 46065.058 | J88: FALSE | M88: 442114351264 | N88: 3 | O88: =(RIGHT(CursosBS_2[[#This Row],[Code]],12)) -> 2026-1-OPC11
A89: 79884 | B89: UPBVirtual | C89: Course Offering | D89: ABC Brightspace Taller 2026-1 -OPC10 | E89: ABC_BRTALL2026-1-OPC10 | H89: TRUE | I89: 46065.057 | J89: FALSE | M89: 442114350657 | N89: 3 | O89: =(RIGHT(CursosBS_2[[#This Row],[Code]],12)) -> 2026-1-OPC10
... A265: 79213 | B265: UPBVirtual | C265: Course Offering | D265: GESTIÓN DE PROYECTOS DE INNOVACIÓN SOCIAL - 202641-52078 | E265: 5569-2029-202641-52078 | H265: TRUE | I265: 46053.671 | J265: FALSE | M265: 442113334934 | N265: 3 | O265: =(RIGHT(CursosBS_2[[#This Row],[Code]],12)) -> 202641-52078
A266: 79212 | B266: UPBVirtual | C266: Course Offering | D266: Inducción a la virtualidad - 202641-52065-52250 | E266: 3313-2040-202641-SM | F266: 46066.708 | H266: TRUE | I266: 46053.026 | J266: FALSE | M266: 442114485214 | N266: 3 | O266: =(RIGHT(CursosBS_2[[#This Row],[Code]],12)) -> 40-202641-SM
A267: 79204 | B267: UPBVirtual | C267: Course Offering | D267: RESEARCH SEMINAR IV: RESEARCH IN PROCESS - 202641-52475 | E267: LGAP-0096-202641-52475 | H267: TRUE | I267: 46052.933 | J267: FALSE | M267: 442113288285 | N267: 3 | O267: =(RIGHT(CursosBS_2[[#This Row],[Code]],12)) -> 202641-52475
A268: 79196 | B268: UPBVirtual | C268: Course Offering | D268: PLANEACIÓN Y FORMULACIÓN DE PROYECTOS - 202641-52171 | E268: 6069-2156-202641-52171 | H268: TRUE | I268: 46052.908 | J268: FALSE | M268: 442113286155 | N268: 3 | O268: =(RIGHT(CursosBS_2[[#This Row],[Code]],12)) -> 202641-52171
A269: 79187 | B269: UPBVirtual | C269: Course Offering | D269: Tecnologías energéticas II - 202641-51373 | E269: 8828-2015-202641-51373 | H269: TRUE | I269: 46052.89 | J269: FALSE | M269: 442113284291 | N269: 3 | O269: =(RIGHT(CursosBS_2[[#This Row],[Code]],12)) -> 202641-51373
A270: 79186 | B270: UPBVirtual | C270: Course Offering | D270: RELIGIONES DEL MUNDO - 202610-31876 | E270: 5568-0008-202610-31876 | H270: TRUE | I270: 46052.806 | J270: FALSE | M270: 442113279375 | N270: 3 | O270: =(RIGHT(CursosBS_2[[#This Row],[Code]],12)) -> 202610-31876
A271: 79185 | B271: UPBVirtual | C271: Course Offering | D271: ÉTICA Y POLÍTICA - 202641-51652 | E271: 5568-0077-202641-51652 | H271: TRUE | I271: 46052.655 | J271: FALSE | M271: 442114487460 | N271: 3 | O271: =(RIGHT(CursosBS_2[[#This Row],[Code]],12)) -> 202641-51652
A272: 79167 | B272: UPBVirtual | C272: Course Offering | D272: Gestión del cronograma, costos y riesgos - 202641-58044 | E272: 6069-2157-202641-58044 | H272: TRUE | I272: 46052.008 | J272: FALSE | M272: 442113248010 | N272: 3 | O272: =(RIGHT(CursosBS_2[[#This Row],[Code]],12)) -> 202641-58044
A273: 79166 | B273: UPBVirtual | C273: Course Offering | D273: Proyecto de intervención - 202641-51999 | E273: 3313-2143-202641-51999 | H273: TRUE | I273: 46051.999 | J273: FALSE | M273: 442113246794 | N273: 3 | O273: =(RIGHT(CursosBS_2[[#This Row],[Code]],12)) -> 202641-51999
A274: 79165 | B274: UPBVirtual | C274: Course Offering | D274: RESEARCH SEMINAR IV: RESEARCH IN PROCESS - 202641-52477 | E274: LGAP-0096-202641-52477 | H274: TRUE | I274: 46051.993 | J274: FALSE | M274: 442113245989 | N274: 3 | O274: =(RIGHT(CursosBS_2[[#This Row],[Code]],12)) -> 202641-52477
A275: 79148 | B275: UPBVirtual | C275: Course Offering | D275: Tecnologías energéticas I - 202641-51367 | E275: 8828-2012-202641-51367 | H275: TRUE | I275: 46051.749 | J275: FALSE | M275: 442113228778 | N275: 3 | O275: =(RIGHT(CursosBS_2[[#This Row],[Code]],12)) -> 202641-51367
A276: 79147 | B276: UPBVirtual | C276: Course Offering | D276: Inducción a la virtualidad - 202641-58882 | E276: 3313-2040-202641-58882 | H276: TRUE | I276: 46051.744 | J276: FALSE | M276: 442113228234 | N276: 3 | O276: =(RIGHT(CursosBS_2[[#This Row],[Code]],12)) -> 202641-58882
A277: 79146 | B277: UPBVirtual | C277: Course Offering | D277: Inducción a la virtualidad - 202641-52004 | E277: 3313-2040-202641-52004 | H277: TRUE | I277: 46051.714 | J277: FALSE | M277: 442113226414 | N277: 3 | O277: =(RIGHT(CursosBS_2[[#This Row],[Code]],12)) -> 202641-52004
A278: 79145 | B278: UPBVirtual | C278: Course Offering | D278: Fortalecimiento de competencias digitales en la investigación docente - QMMaestroP(T) | E278: PGME-3106-MaestroP | H278: TRUE | I278: 46051.675 | J278: FALSE | M278: 442113224362 | N278: 3 | O278: =(RIGHT(CursosBS_2[[#This Row],[Code]],12)) -> 106-MaestroP
... A309: 79036 | B309: UPBVirtual | C309: Course Offering | D309: Inducción a la virtualidad - 202641-52422 | E309: 3313-2040-202641-52422 | H309: TRUE | I309: 46049.988 | J309: FALSE | M309: 442113188788 | N309: 3 | O309: =(RIGHT(CursosBS_2[[#This Row],[Code]],12)) -> 202641-52422
A310: 79035 | B310: UPBVirtual | C310: Course Offering | D310: XXXInducción a la virtualidad - 202641-51650 | E310: XXX3313-2040--202641-51650 | H310: FALSE | I310: 46049.987 | J310: FALSE | L310: 46050.89 | M310: 442113188491 | N310: 3 | O310: =(RIGHT(CursosBS_2[[#This Row],[Code]],12)) -> 202641-51650
A311: 79034 | B311: UPBVirtual | C311: Course Offering | D311: XXXInducción a la virtualidad - 202641-51650 | E311: XXX3313-2040--202641-51650 | H311: FALSE | I311: 46049.986 | J311: FALSE | L311: 46050.89 | M311: 442113188489 | N311: 3 | O311: =(RIGHT(CursosBS_2[[#This Row],[Code]],12)) -> 202641-51650
A312: 79033 | B312: UPBVirtual | C312: Course Offering | D312: Inducción a la virtualidad - 202641-51650 | E312: 3313-2040-202641-51650 | H312: TRUE | I312: 46049.984 | J312: FALSE | M312: 442113188807 | N312: 3 | O312: =(RIGHT(CursosBS_2[[#This Row],[Code]],12)) -> 202641-51650
A313: 79032 | B313: UPBVirtual | C313: Course Offering | D313: Inducción a la virtualidad - 202641-51691 | E313: 3313-2040-202641-51691 | H313: TRUE | I313: 46049.983 | J313: FALSE | M313: 442113188829 | N313: 3 | O313: =(RIGHT(CursosBS_2[[#This Row],[Code]],12)) -> 202641-51691
A314: 79025 | B314: UPBVirtual | C314: Course Offering | D314: Ética en la red - 202641-51938 | E314: 5568-0074-202641-51938 | H314: FALSE | I314: 46049.982 | J314: FALSE | M314: 442113650775 | N314: 3 | O314: =(RIGHT(CursosBS_2[[#This Row],[Code]],12)) -> 202641-51938
A315: 79024 | B315: UPBVirtual | C315: Course Offering | D315: Inducción a la virtualidad - 202641-51937 | E315: 3313-2040-202641-51937 | H315: TRUE | I315: 46049.981 | J315: FALSE | M315: 442113188868 | N315: 3 | O315: =(RIGHT(CursosBS_2[[#This Row],[Code]],12)) -> 202641-51937
A316: 79023 | B316: UPBVirtual | C316: Course Offering | D316: Inducción a la virtualidad - 202641-52065 | E316: 5557-0044-202641-52065 | H316: TRUE | I316: 46049.98 | J316: FALSE | M316: 442113188901 | N316: 3 | O316: =(RIGHT(CursosBS_2[[#This Row],[Code]],12)) -> 202641-52065
A317: 79014 | B317: UPBVirtual | C317: Course Offering | D317: Maestria-Manejo de la información en el ecosistema digital - 202641-51858 | E317: 5557-2061-202641-51858 | H317: TRUE | I317: 46049.979 | J317: FALSE | M317: 442113844048 | N317: 3 | O317: =(RIGHT(CursosBS_2[[#This Row],[Code]],12)) -> 202641-51858
A318: 79013 | B318: UPBVirtual | C318: Course Offering | D318: Inducción a la virtualidad - 202641-51986 | E318: 3313-2040-202641-51986 | H318: TRUE | I318: 46049.978 | J318: FALSE | M318: 442113189006 | N318: 3 | O318: =(RIGHT(CursosBS_2[[#This Row],[Code]],12)) -> 202641-51986
A319: 79012 | B319: UPBVirtual | C319: Course Offering | D319: Inducción a la virtualidad - 202641-52050 | E319: 3313-2040-202641-52050 | H319: TRUE | I319: 46049.977 | J319: FALSE | M319: 442113189032 | N319: 3 | O319: =(RIGHT(CursosBS_2[[#This Row],[Code]],12)) -> 202641-52050
A320: 79011 | B320: UPBVirtual | C320: Course Offering | D320: Inducción a la virtualidad - 202641-51850 | E320: 3313-2040-202641-51850 | H320: FALSE | I320: 46049.976 | J320: FALSE | M320: 442113280876 | N320: 3 | O320: =(RIGHT(CursosBS_2[[#This Row],[Code]],12)) -> 202641-51850
A321: 79001 | B321: UPBVirtual | C321: Course Offering | D321: ÉTICA DE LAS ORGANIZACIONES - 202641-58384 | E321: 5568-0073-202641-58384 | H321: TRUE | I321: 46049.975 | J321: FALSE | M321: 442113189136 | N321: 3 | O321: =(RIGHT(CursosBS_2[[#This Row],[Code]],12)) -> 202641-58384
A322: 78991 | B322: UPBVirtual | C322: Course Offering | D322: XXXÉTICA DE LAS ORGANIZACIONES - 202641-58384 | E322: XXX5568-0073--202641-58384 | H322: FALSE | I322: 46049.974 | J322: FALSE | L322: 46050.873 | M322: 442113186804 | N322: 3 | O322: =(RIGHT(CursosBS_2[[#This Row],[Code]],12)) -> 202641-58384
A323: 78980 | B323: UPBVirtual | C323: Course Offering | D323: INTRODUCCIÓN A LA ENFERMERÍA - 202610-10092 | E323: 4441-0001-202610-10092 | H323: TRUE | I323: 46049.916 | J323: FALSE | M323: 442113124328 | N323: 3 | O323: =(RIGHT(CursosBS_2[[#This Row],[Code]],12)) -> 202610-10092
A324: 78979 | B324: UPBVirtual | C324: Course Offering | D324: READING COMPREHENSION STRATEGIES - 202650-50856 | E324: IDIO-0014-202650-50856 | H324: TRUE | I324: 46049.674 | J324: FALSE | M324: 442113106227 | N324: 3 | O324: =(RIGHT(CursosBS_2[[#This Row],[Code]],12)) -> 202650-50856
A325: 78978 | B325: UPBVirtual | C325: Course Offering | D325: READING COMPREHENSION STRATEGIES - 202650-50855 | E325: IDIO-0014-202650-50855 | H325: TRUE | I325: 46049.671 | J325: FALSE | M325: 442113105945 | N325: 3 | O325: =(RIGHT(CursosBS_2[[#This Row],[Code]],12)) -> 202650-50855
A326: 78977 | B326: UPBVirtual | C326: Course Offering | D326: READING COMPREHENSION STRATEGIES - 202650-50014 | E326: IDIO-0014-202650-50014 | H326: TRUE | I326: 46049.67 | J326: FALSE | M326: 442113105699 | N326: 3 | O326: =(RIGHT(CursosBS_2[[#This Row],[Code]],12)) -> 202650-50014
A327: 78976 | B327: UPBVirtual | C327: Course Offering | D327: Diálogos con la tradición literaria 1 (antigüedad) - QMMaestroP(R) | E327: 5564-0126-MaestroP | H327: TRUE | I327: 46049.582 | J327: FALSE | M327: 442114823779 | N327: 3 | O327: =(RIGHT(CursosBS_2[[#This Row],[Code]],12)) -> 126-MaestroP
A328: 78949 | B328: UPBVirtual | C328: Course Offering | D328: Investigación Social II - 202641-51998 | E328: 3313-2027-202641-51998 | H328: TRUE | I328: 46048.877 | J328: FALSE | M328: 442113052434 | N328: 3 | O328: =(RIGHT(CursosBS_2[[#This Row],[Code]],12)) -> 202641-51998
A329: 78927 | B329: UPBVirtual | C329: Course Offering | D329: GESTIÓN ESTRATÉGICA - 202610-31508 | E329: CEOE-0321-202610-31508 | H329: TRUE | I329: 46046.881 | J329: FALSE | M329: 442112948444 | N329: 3 | O329: =(RIGHT(CursosBS_2[[#This Row],[Code]],12)) -> 202610-31508
A330: 78921 | B330: UPBVirtual | C330: Course Offering | D330: EJERCICIO INVESTIGATIVO II - 202641-58845 | E330: 3313-2055-202641-58845 | H330: FALSE | I330: 46045.919 | J330: FALSE | M330: 442113032014 | N330: 3 | O330: =(RIGHT(CursosBS_2[[#This Row],[Code]],12)) -> 202641-58845
A331: 78913 | B331: UPBVirtual | C331: Course Offering | D331: Sistemas de Información y Medición en Gestión Humana - 202641-52000 | E331: 5566-2047V-202641-52000 | H331: TRUE | I331: 46045.737 | J331: FALSE | M331: 442112885187 | N331: 3 | O331: =(RIGHT(CursosBS_2[[#This Row],[Code]],12)) -> 202641-52000
A332: 78896 | B332: UPBVirtual | C332: Course Offering | D332: ÉTICA DE LAS ORGANIZACIONES - 202641-58385 | E332: 5568-0073-202641-58385 | H332: TRUE | I332: 46044.899 | J332: FALSE | M332: 442112849745 | N332: 3 | O332: =(RIGHT(CursosBS_2[[#This Row],[Code]],12)) -> 202641-58385
...

Sheet MateriaCurso
A1: 5557-2007 | B1: =A1&"-MaestroC" -> 5557-2007-MaestroC
A2: 5559-2090V | B2: =A2&"-MaestroC" -> 5559-2090V-MaestroC
A3: 5559-2057V | B3: =A3&"-MaestroC" -> 5559-2057V-MaestroC
A4: 6611-2020V | B4: =A4&"-MaestroC" -> 6611-2020V-MaestroC
A5: 6069-2060 | B5: =A5&"-MaestroC" -> 6069-2060-MaestroC
A6: 8827-2009 | B6: =A6&"-MaestroC" -> 8827-2009-MaestroC
A7: 9937-2002 | B7: =A7&"-MaestroC" -> 9937-2002-MaestroC
A8: 3313-2053 | B8: =A8&"-MaestroC" -> 3313-2053-MaestroC
A9: 8828-2013 | B9: =A9&"-MaestroC" -> 8828-2013-MaestroC
A10: 3313-2129 | B10: =A10&"-MaestroC" -> 3313-2129-MaestroC
A11: 8828-2016 | B11: =A11&"-MaestroC" -> 8828-2016-MaestroC
